{"地震": 1439, "九寨沟": 1284, "爱": 650, "四川": 339, "吴京": 323, "##": 321, "链接": 312, "网页": 309, "捐": 270, "爱心": 245, "微博": 238, "刚刚": 235, "援助": 234, "无限": 233, "伸出": 233, "之手": 233, "每份": 232, "能量": 232, "充满": 232, "献出": 230, "微小": 230, "善举": 230, "凝聚": 230, "级": 208, "救援": 207, "发生": 189, "旅行": 187, "7.0": 174, "捐款": 174, "亿": 162, "月": 155, "救": 151, "壹线": 143, "时": 142, "日": 139, "回应": 134, "逼": 128, "紧急": 106, "网友": 99, "万": 94, "心": 94, "慈善": 92, "灾区": 90, "算命": 90, "算卦": 90, "对得起": 86, "良心": 84, "景区": 84, "生活": 82, "搞笑": 79, "摄影": 78, "九寨沟县": 77, "九寨": 76, "中": 76, "战狼": 74, "100": 73, "海子": 73, "关注": 73, "说": 72, "票房": 70, "李连杰": 69, "年": 63, "归来": 63, "震后": 58, "恢复": 55, "祈福": 55, "大卖": 53, "时间": 52, "受损": 51, "消防": 50, "瑶池": 49, "游客": 48, "瀑": 48, "碧水": 48, "明星": 47, "翠海叠": 47, "分": 44, "元": 44, "火花": 44, "瀑布": 43, "四川省": 43, "中国": 42, "↓": 42, "发现": 41, "海": 41, "开学": 41, "生命": 40, "希望": 39, "总有": 39, "误会": 38, "公里": 38, "方式": 37, "澄清": 37, "成都": 37, "度": 36, "╱": 36, "第一": 36, "五花海": 36, "现场": 35, "美丽": 35, "两周": 35, "水": 34, "10": 34, "坦言": 33, "道德": 33, "车辆": 33, "前": 33, "愿": 33, "依在": 33, "旅游": 32, "应急": 32, "钱": 31, "绑架": 31, "蜡烛": 31, "震中": 31, "神奇": 31, "工作": 31, "21": 30, "视频": 30, "学习": 30, "受伤": 30, "平安": 30, "鼓励": 29, "19": 29, "航拍": 29, "发布": 28, "夫妇": 28, "诺日朗": 28, "阿坝州": 28, "想": 27, "大哥": 27, "13": 27, "转发": 27, "补妆": 27, "黯淡": 27, "博文": 27, "公司": 26, "死亡": 26, "实拍": 26, "遇难者": 25, "台风": 25, "秒": 25, "汶川": 25, "日晚": 25, "美": 25, "重建": 24, "童话世界": 24, "近日": 23, "努力": 23, "发表": 23, "公益": 23, "2017": 22, "记者": 22, "一度": 22, "妆容": 22, "大部分": 22, "支持": 22, "葡萄": 22, "我会": 21, "卖": 21, "专家": 21, "大自然": 21, "生态": 21, "保护": 21, "著名景点": 21, "加油": 21, "排查": 21, "首次": 20, "开口": 20, "太": 20, "门票": 20, "纷纷": 20, "要火": 20, "qifei192": 20, "点": 20, "qifei190": 20, "头条": 20, "人民网": 20, "地矿局": 20, "拜拜": 19, "25": 19, "砸": 19, "撤离": 19, "实地": 19, "文章": 19, "名": 19, "08": 19, "工作人员": 19, "采访": 18, "谢楠": 18, "qifei193": 18, "途中": 18, "消防官兵": 18, "情况": 18, "搜救": 18, "50": 18, "能力": 18, "救灾": 18, "人员": 18, "群众": 18, "自我": 18, "修复": 18, "地质灾害": 18, "做": 18, "项目": 18, "美景": 17, "新疆": 17, "孩子": 17, "一名": 17, "真的": 17, "消息": 17, "伤员": 17, "　": 17, "忍不住": 17, "一把": 17, "放弃": 17, "棒": 16, "北纬": 16, "东经": 16, "地方": 16, "http": 16, "此前": 16, "飙升": 16, "n": 16, "盒": 16, "展开": 16, "一场": 16, "震区": 16, "南充": 16, "灾害": 16, "自净": 16, "转移": 16, "道路": 16, "人间天堂": 16, "┈": 16, "100909848": 15, "台网": 15, "在": 15, "正式": 15, "牵动": 15, "20": 15, "侧翻": 15, "前段时间": 15, "一百万": 15, "称为": 15, "六绝": 15, "奇景": 15, "惊叹": 15, "恢复能力": 15, "悲伤": 15, "之光": 14, "社会": 14, "全文": 14, "岁": 14, "挺进": 14, "路": 14, "清澈": 14, "陈晓清": 14, "火": 14, "消防员": 14, "华地": 14, "多家": 14, "自救": 14, "微博去": 14, "音乐": 14, "天鸽": 13, "受访": 13, "拍": 13, "新浪": 13, "40": 13, "c": 13, "低调": 13, "24": 13, "陈先生": 13, "外": 13, "号": 13, "酒店": 13, "支队": 13, "深度": 13, "一位": 13, "疏散": 13, "遗体": 13, "武警": 13, "收入": 13, "全景": 13, "余震": 13, "新闻": 13, "吃": 13, "回来": 13, "展现出": 13, "强大": 13, "碧蓝": 13, "请": 13, "开通": 13, "道": 13, "勿忘": 12, "永不": 12, "灭": 12, "测定": 12, "至少": 12, "损失": 12, "称向": 12, "对此": 12, "众": 12, "破纪录": 12, "捐出": 12, "妻女": 12, "话筒": 12, "一家": 12, "遇": 12, "15": 12, "医院": 12, "爆炸": 12, "good": 12, "万元": 12, "军人": 12, "一亿": 12, "转载": 12, "em": 12, "张钧": 12, "甯": 12, "称会用": 11, "世界": 11, "初步": 11, "17": 11, "接受": 11, "捐钱": 11, "没": 11, "献爱心": 11, "收费": 11, "最新": 11, "启动": 11, "解释": 11, "灾后": 11, "小时": 11, "可爱": 11, "天津": 11, "80": 11, "电影票房": 11, "景点": 11, "震源": 11, "戳": 11, "qifei191": 11, "组织": 11, "畅通": 11, "被困": 11, "分享": 11, "严重破坏": 11, "经历": 11, "360": 11, "海水": 11, "手机": 11, "一个月": 11, "力量": 11, "救援队": 11, "祈祷": 11, "扩散": 11, "皮": 11, "达": 10, "一个亿": 10, "全国同胞": 10, "师哥": 10, "停车场": 10, "次": 10, "山体": 10, "未来": 10, "上午": 10, "骨折": 10, "台湾": 10, "总队": 10, "陇南": 10, "熊猫": 10, "感谢": 10, "巴中": 10, "放在": 10, "第一位": 10, "天堂": 10, "阿坝": 10, "海西": 10, "北约": 10, "5.3": 10, "站": 10, "电话": 10, "官兵": 10, "图": 10, "通道": 10, "队伍": 10, "方向": 10, "18": 10, "几个": 10, "失语": 10, "出院": 10, "不吐": 10, "微笑": 9, "成都市": 9, "报": 9, "感觉": 9, "同胞": 9, "玉树": 9, "300": 9, "人次": 9, "盒饭": 9, "60": 9, "方便面": 9, "广州": 9, "一辆": 9, "方向向": 9, "横": 9, "预案": 9, "环境": 9, "包括": 9, "镜海": 9, "前往": 9, "义工": 9, "刘亦菲": 9, "孙俪": 9, "度过难关": 9, "千米": 9, "评估": 9, "问": 9, "江油": 9, "驰援": 9, "政府": 9, "危险": 9, "字": 9, "电影": 9, "生态系统": 9, "30": 9, "未": 9, "交通": 9, "网": 9, "捐少": 9, "推移": 9, "高速": 9, "供电": 9, "央企": 9, "绿色通道": 9, "赞": 9, "狼": 9, "全国": 9, "解析": 9, "杨洋": 9, "北京": 9, "机器人": 9, "忆": 9, "刘信": 8, "摊手": 8, "回复": 8, "轻武器": 8, "987": 8, "捐太少": 8, "此事": 8, "参加": 8, "甘南": 8, "环线": 8, "查看": 8, "新": 8, "连夜": 8, "点赞": 8, "失踪": 8, "王宝强": 8, "离婚": 8, "亲亲": 8, "灾情": 8, "集结": 8, "齐心协力": 8, "雅安": 8, "度假": 8, "下午": 8, "版": 8, "平武": 8, "志愿者": 8, "女儿": 8, "中心": 8, "废墟": 8, "找到": 8, "辛苦": 8, "今日": 8, "事": 8, "中队": 8, "微辣": 8, "Video": 8, "技巧": 8, "天佑": 8, "央视": 8, "鼓掌": 8, "这是": 8, "受灾": 8, "企业": 8, "直播": 8, "房屋": 8, "14": 8, "漳扎镇": 8, "一条": 8, "八个": 8, "霸气": 8, "12": 8, "可惜": 8, "躲避": 8, "信息": 8, "祖国": 8, "有人": 8, "安好": 8, "怒": 8, "天灾": 7, "33.2": 7, "103.8": 7, "最终": 7, "数据": 7, "哥": 7, "活该": 7, "车": 7, "事儿": 7, "娱乐": 7, "自行车": 7, "一毛不拔": 7, "消防支队": 7, "小轿车": 7, "服务": 7, "中科院": 7, "山地": 7, "研究所": 7, "勘察": 7, "金铃": 7, "信心": 7, "巨石": 7, "正": 7, "休息": 7, "死": 7, "2013": 7, "马航": 7, "2014": 7, "2015": 7, "2016": 7, "依然": 7, "急救": 7, "施救": 7, "喊话": 7, "昔日": 7, "省": 7, "绵阳": 7, "捐赠": 7, "永竹村": 7, "听": 7, "省林业厅": 7, "搜": 7, "重伤": 7, "安置": 7, "最美": 7, "父母": 7, "永远": 7, "早日": 7, "死角": 7, "机票": 7, "11": 7, "围观": 7, "县城": 7, "现实": 7, "骂": 7, "云": 7, "文字版": 7, "长微博": 7, "人间仙境": 7, "距离": 7, "抗震救灾": 7, "计划": 7, "回": 7, "一个个": 7, "甘肃": 7, "倒塌": 7, "银行": 7, "黄龙": 7, "通信": 7, "投入": 7, "90": 7, "防灾": 7, "知识": 7, "王俊凯": 7, "金九": 7, "成人礼": 7, "背后": 7, "突如其来": 7, "通行": 7, "发怒": 7, "不想": 6, "完": 6, "厨房": 6, "问问": 6, "6.0": 6, "地震台": 6, "网速": 6, "为准": 6, "楼": 6, "壳子": 6, "腿": 6, "软": 6, "配": 6, "个别人": 6, "发": 6, "天府": 6, "新城": 6, "贵": 6, "向小田": 6, "太贵": 6, "李": 6, "沿途": 6, "建筑": 6, "排": 6, "落石": 6, "公安": 6, "12301": 6, "地区": 6, "国家": 6, "热线": 6, "微信": 6, "直击": 6, "处": 6, "感受": 6, "风景": 6, "护士": 6, "赶赴": 6, "遇难": 6, "道理": 6, "垮塌": 6, "泪": 6, "位": 6, "救援车辆": 6, "民间": 6, "失联": 6, "曙光": 6, "45": 6, "昨日": 6, "最棒": 6, "临时": 6, "选择": 6, "°": 6, "O": 6, "图片": 6, "救出": 6, "灾难": 6, "想起": 6, "日本": 6, "挖掘机": 6, "热": 6, "介绍": 6, "评论": 6, "33.20": 6, "103.82": 6, "400": 6, "半月": 6, "via": 6, "日报": 6, "居民": 6, "8.8": 6, "退": 6, "几天": 6, "很大": 6, "犬": 6, "台": 6, "抢险": 6, "石化": 6, "文县": 6, "23": 6, "吴京战": 6, "广场": 6, "不捐": 6, "七级": 6, "强震": 6, "t": 6, "有限公司": 6, "原本": 6, "得出结论": 6, "不宜": 6, "TTKK22": 6, "威武": 6, "戏子": 6, "重创": 6, "保障": 6, "销售": 6, "客户": 6, "五彩": 6, "绳": 6, "挽救": 6, "怒骂": 6, "帮": 5, "明天": 5, "顶": 5, "沟里": 5, "妻子": 5, "下车": 5, "出行": 5, "提示": 5, "航空公司": 5, "消失": 5, "连续": 5, "奥特曼": 5, "川": 5, "学会": 5, "时有": 5, "注意事项": 5, "物资": 5, "妇女": 5, "奔赴": 5, "奉献": 5, "能": 5, "路段": 5, "检查": 5, "劝告": 5, "同意": 5, "混乱": 5, "武警官兵": 5, "埋": 5, "地灾": 5, "防治": 5, "产业": 5, "发展": 5, "基础设施": 5, "公共服务": 5, "城乡": 5, "住房": 5, "五个": 5, "重点": 5, "担心": 5, "身边": 5, "记得": 5, "兔子": 5, "逆行": 5, "逃生": 5, "听到": 5, "漂亮": 5, "武汉": 5, "朋友": 5, "导致": 5, "来": 5, "避难": 5, "一辈子": 5, "人心": 5, "通往": 5, "称": 5, "民警": 5, "颤抖": 5, "国人": 5, "现场直播": 5, "全": 5, "捐多": 5, "吃惊": 5, "公开": 5, "免费": 5, "突发状况": 5, "3000": 5, "一件": 5, "39": 5, "松潘县": 5, "66": 5, "时许": 5, "轿车": 5, "美好": 5, "提醒": 5, "金融": 5, "寻亲": 5, "石油": 5, "赵丽颖": 5, "到来": 5, "关乎": 5, "一篇": 5, "公布": 5, "不好": 5, "辆": 5, "八月": 5, "仙境": 5, "详情": 5, "提供": 5, "女孩儿": 5, "成功": 5, "心中": 5, "e282": 5, "qifei31": 5, "遗憾": 5, "总会": 5, "热门": 5, "澳门": 5, "多处": 5, "QQ": 5, "茶子": 5, "国内": 5, "贡献": 5, "物品": 5, "四川人": 5, "很": 5, "黄岭": 5, "活动": 5, "健康": 5, "遭受": 5, "宝石": 5, "变得": 5, "灰黄": 5, "浑浊": 5, "杂乱": 5, "网易": 4, "公开课": 4, "赵薇家": 4, "玩意": 4, "住宿": 4, "舍不得": 4, "内心": 4, "有种": 4, "多行不义必自毙": 4, "估计": 4, "一群": 4, "默哀": 4, "一点": 4, "n2013": 4, "五一": 4, "骑": 4, "G318": 4, "川藏线": 4, "芦山": 4, "n2017": 4, "自驾": 4, "川西": 4, "环绕": 4, "巧合": 4, "思考": 4, "巅锋": 4, "说起": 4, "月初": 4, "寻人": 4, "车子": 4, "进沟": 4, "失散": 4, "分批": 4, "走散": 4, "伤势": 4, "大碍": 4, "急需": 4, "王锦滔": 4, "成": 4, "见状": 4, "勘查": 4, "幸福": 4, "名胜区": 4, "致敬": 4, "区": 4, "中午": 4, "贪便宜": 4, "大巴": 4, "53": 4, "女士": 4, "花": 4, "到": 4, "塔罗牌": 4, "占卜": 4, "哥们": 4, "身": 4, "身份": 4, "直升机": 4, "挑战": 4, "全线": 4, "早报": 4, "500": 4, "善款": 4, "南京": 4, "团体": 4, "三口": 4, "机场": 4, "汽车": 4, "瓦房": 4, "坍塌": 4, "屋里": 4, "两人": 4, "不肯": 4, "耐心": 4, "屋主": 4, "风景区": 4, "特效": 4, "家": 4, "得意": 4, "阴险": 4, "昨天": 4, "演唱会": 4, "二次": 4, "人数": 4, "增至": 4, "务工人员": 4, "母亲": 4, "跑": 4, "员工": 4, "突遇": 4, "牙齿": 4, "重庆": 4, "吴京应": 4, "之地": 4, "一路": 4, "部队": 4, "震灾": 4, "宣传片": 4, "用不上": 4, "多学": 4, "多记": 4, "紧要": 4, "十六": 4, "番": 4, "勇敢": 4, "导游": 4, "手中": 4, "女孩": 4, "身影": 4, "理赔": 4, "不要脸": 4, "抢": 4, "大酒店": 4, "分析": 4, "滑坡": 4, "远离": 4, "敬礼": 4, "太阳": 4, "创伤": 4, "电力": 4, "前方": 4, "原文": 4, "祝福": 4, "梦": 4, "带来": 4, "改签": 4, "滞留": 4, "保证": 4, "下载": 4, "张": 4, "已致": 4, "核查": 4, "不到": 4, "寿险": 4, "单位": 4, "广东": 4, "圈": 4, "交通运输": 4, "doge": 4, "成绵": 4, "徒步": 4, "礼物": 4, "蓝筹": 4, "长": 4, "电力企业": 4, "备足": 4, "库存": 4, "响": 4, "金融服务": 4, "退票": 4, "受": 4, "行": 4, "MV": 4, "黄晓明": 4, "求助": 4, "捐不捐": 4, "微": 4, "富国": 4, "上市": 4, "公司股票": 4, "质押": 4, "信用": 4, "贷": 4, "成熟性": 4, "物业": 4, "spv": 4, "品鉴": 4, "moonzl888": 4, "若尔盖县": 4, "每日": 4, "女人": 4, "还会": 4, "全友": 4, "「": 4, "离别": 4, "来到": 4, "送": 4, "云南": 4, "收": 4, "中巴": 4, "合力": 4, "节日": 4, "惨遭": 4, "录制": 4, "毁": 4, "昨晚": 4, "罗川": 4, "滨": 4, "所有人": 4, "少": 4, "赚": 4, "科技": 4, "影响": 4, "万分": 4, "首歌": 4, "众星": 4, "出门": 4, "热门话题": 4, "窗子": 4, "住": 4, "顺利": 4, "彩虹": 4, "V": 4, "免": 4, "赴": 4, "大熊猫": 4, "珍稀": 4, "野生": 4, "动植物": 4, "捐款捐物": 4, "亲历": 4, "笑": 4, "拖车": 4, "专用汽车": 4, "懂": 4, "车型": 4, "配置": 4, "蓝色": 4, "美泉": 4, "摄影师": 4, "创业": 4, "服大疆": 4, "价值": 4, "大连": 4, "星海": 4, "玩大疆": 4, "很爽": 4, "太穷": 4, "烧": 4, "无人机": 4, "90%": 4, "下岗": 4, "只用": 4, "一台": 4, "小明": 4, "代表": 4, "智能化": 4, "进程": 4, "加快": 4, "亦庄": 4, "短": 4, "郑爽": 4, "最全": 4, "抓狂": 4, "房贷": 4, "安庆": 4, "户": 4, "新华社": 4, "说话": 4, "今晚": 4, "＂": 4, "林俊杰": 4, "彭于": 4, "晏": 4, "售价": 4, "昂贵": 4, "子弟兵": 4, "清清": 4, "写": 4, "文山": 4, "遍": 4, "轩缘": 4, "双子": 4, "何时休": 4, "本来": 3, "风貌": 3, "推荐": 3, "演出": 3, "千古": 3, "提议": 3, "留意到": 3, "我家": 3, "一家人": 3, "占": 3, "妈": 3, "破坏": 3, "身价": 3, "确实": 3, "此人": 3, "报道": 3, "特有": 3, "标志性": 3, "长城": 3, "想必": 3, "故宫": 3, "断裂": 3, "堤坝": 3, "崩塌": 3, "生病": 3, "交通阻塞": 3, "公众": 3, "做主": 3, "过后": 3, "京报": 3, "助力": 3, "湖泊": 3, "怀孕": 3, "不顾": 3, "怀有": 3, "身孕": 3, "王爱花": 3, "同事": 3, "次日": 3, "伤": 3, "报团": 3, "甘肃省": 3, "做好": 3, "兰州": 3, "画面": 3, "很强": 3, "精河": 3, "方法": 3, "男人": 3, "忍耐": 3, "有限": 3, "西林": 3, "凤腾": 3, "通航": 3, "空中客车": 3, "H125": 3, "广汉": 3, "起飞": 3, "飞行": 3, "航空": 3, "物语": 3, "场景": 3, "对不起": 3, "出生": 3, "一线": 3, "朋友圈": 3, "逻辑": 3, "跟随": 3, "交警": 3, "九黄": 3, "参与": 3, "安徽": 3, "路边": 3, "老师": 3, "突发": 3, "演员": 3, "火速": 3, "观众": 3, "凌晨": 3, "房子": 3, "有钱": 3, "狗": 3, "一部": 3, "意外": 3, "间": 3, "雨": 3, "泸州": 3, "余人": 3, "执行": 3, "昏厥": 3, "醒": 3, "26": 3, "不幸": 3, "做鬼脸": 3, "一种": 3, "旅客": 3, "牵动人心": 3, "昨夜": 3, "赶往": 3, "安心": 3, "担当": 3, "哭": 3, "建": 3, "月亮": 3, "地点": 3, "自愿": 3, "耶": 3, "预测": 3, "死伤": 3, "难": 3, "研究": 3, "过程": 3, "洲际": 3, "力图": 3, "局": 3, "网上": 3, "谣言": 3, "指挥": 3, "疏导": 3, "面": 3, "听说": 3, "粉丝": 3, "送给": 3, "截止": 3, "累计": 3, "沟通": 3, "夏风秋云": 3, "Y": 3, "回忆": 3, "位于": 3, "转": 3, "妈妈": 3, "业务": 3, "市场": 3, "高清": 3, "西部": 3, "地笑": 3, "越来越": 3, "靠近": 3, "确保": 3, "发布会": 3, "指挥部": 3, "命": 3, "2010": 3, "信": 3, "自然灾害": 3, "条": 3, "万余": 3, "包": 3, "247": 3, "排除": 3, "事情": 3, "里": 3, "关系": 3, "堪比": 3, "走": 3, "珠海": 3, "满目疮痍": 3, "路网": 3, "运行": 3, "禁止": 3, "联合": 3, "专家组": 3, "门口": 3, "剩余": 3, "多人": 3, "可怕": 3, "得": 3, "拉升": 3, "抱抱": 3, "米": 3, "现": 3, "175": 3, "设备": 3, "北川": 3, "休假": 3, "滩": 3, "堰塞湖": 3, "乡镇": 3, "镇": 3, "交": 3, "调查": 3, "专业": 3, "报告": 3, "睡觉": 3, "响应": 3, "文明": 3, "半个": 3, "风去": 3, "云不回": 3, "浪花": 3, "一朵朵": 3, "救护车": 3, "派出": 3, "指出": 3, "中文": 3, "国际": 3, "会商": 3, "级别": 3, "强度": 3, "家私": 3, "第二天": 3, "200": 3, "工资": 3, "7000": 3, "近期": 3, "高": 3, "特别": 3, "一块": 3, "快讯": 3, "县": 3, "分钟": 3, "收到": 3, "谢谢": 3, "风光": 3, "拳头": 3, "厦门市": 3, "众筹": 3, "筹": 3, "路况": 3, "发出": 3, "icon": 3, "八卦": 3, "壹": 3, "周汇": 3, "阳光": 3, "亲爱": 3, "挺": 3, "喷子": 3, "到手": 3, "他称": 3, "背影": 3, "副": 3, "千里": 3, "憧憬": 3, "脆红": 3, "爷爷奶奶": 3, "前去": 3, "一趟": 3, "境内": 3, "森林": 3, "看点": 3, "一份": 3, "垃圾": 3, "向往": 3, "舟曲县": 3, "83": 3, "85": 3, "市": 3, "105": 3, "285": 3, "降临": 3, "今夜": 3, "闭眼": 3, "一分钟": 3, "随意": 3, "车祸": 3, "手术": 3, "撤出": 3, "自然": 3, "赈灾": 3, "门": 3, "微风": 3, "htt": 3, "16": 3, "环境影响": 3, "座谈会": 3, "依旧": 3, "玉": 3, "瘦": 3, "这场": 3, "指责": 3, "厅": 3, "万达": 3, "股份": 3, "一方有难": 3, "八方支援": 3, "想要": 3, "流量": 3, "好好": 3, "东西": 3, "大火": 3, "诛": 3, "仙": 3, "高颜值": 3, "致房": 3, "顾客": 3, "结账": 3, "没想到": 3, "厉害": 3, "停下": 3, "冰棍": 3, "注意安全": 3, "喜欢": 3, "七夕": 3, "照片": 3, "去过": 3, "接收": 3, "灾民": 3, "歌曲": 3, "喷人": 3, "先": 3, "安安静静": 3, "就行了": 3, "能救": 3, "查": 3, "伤心": 3, "开车": 3, "捂脸": 3, "篇": 3, "向": 3, "独学": 2, "无友": 2, "孤陋": 2, "寡闻": 2, "诚意": 2, "挡住": 2, "石头": 2, "那一刻": 2, "嫁给": 2, "赐教": 2, "情": 2, "深圳": 2, "妹": 2, "曝光": 2, "直呼": 2, "灾": 2, "搞不懂": 2, "李俊": 2, "仔": 2, "眼里": 2, "傻": 2, "很想": 2, "心态": 2, "一毛钱": 2, "键盘": 2, "侠": 2, "强": 2, "反正": 2, "人": 2, "吴京开": 2, "毛病": 2, "健身": 2, "问答": 2, "造": 2, "可拨打": 2, "寻求": 2, "OTA": 2, "机构": 2, "石块": 2, "变形": 2, "滑落": 2, "拒绝": 2, "此时此刻": 2, "唯一": 2, "罕见": 2, "高山": 2, "群": 2, "瀑布群": 2, "钙华滩": 2, "流为": 2, "主体": 2, "1992": 2, "联合国教科文组织": 2, "列入": 2, "自然遗产": 2, "名录": 2, "大妈": 2, "感慨": 2, "惹祸": 2, "岁任": 2, "双腿": 2, "害怕": 2, "玩": 2, "同学": 2, "详细": 2, "核实": 2, "队": 2, "开": 2, "珍珠": 2, "商报": 2, "滴": 2, "3.0": 2, "外伤": 2, "出血": 2, "日至": 2, "6.6": 2, "接连": 2, "伤口": 2, "变": 2, "亮明": 2, "拍摄": 2, "惋惜": 2, "辅警": 2, "亲吻": 2, "脸": 2, "29": 2, "父亲": 2, "王八蛋": 2, "网络": 2, "进发": 2, "是从": 2, "私家车": 2, "实行": 2, "百雀羚": 2, "寻找": 2, "快报": 2, "禄口": 2, "偶遇": 2, "王刚": 2, "开会": 2, "舞台剧": 2, "台上": 2, "意识": 2, "台下": 2, "演艺": 2, "确认": 2, "形容": 2, "是因为": 2, "作品": 2, "凤凰网": 2, "爆点": 2, "期盼": 2, "无辜": 2, "可怜": 2, "旅途": 2, "微博热": 2, "乐观": 2, "493": 2, "共计": 2, "逆着": 2, "人流": 2, "背": 2, "张国全": 2, "十三": 2, "士官": 2, "战友": 2, "奔逃": 2, "逆": 2, "行者": 2, "孝心": 2, "女子": 2, "女性": 2, "喝多": 2, "女护士": 2, "手指": 2, "撬开": 2, "中国人民解放军": 2, "总医院": 2, "护": 2, "士童": 2, "红艳": 2, "游玩": 2, "多岁": 2, "躺": 2, "地上": 2, "不停": 2, "抽搐": 2, "咬住": 2, "舌头": 2, "懒鱼": 2, "航班": 2, "鬼门关": 2, "特警": 2, "取消": 2, "承担": 2, "接到": 2, "旅行社": 2, "乐播": 2, "din": 2, "推撞": 2, "无数": 2, "引导": 2, "司": 2, "激动": 2, "境区": 2, "咱钱少": 2, "黄河": 2, "长江": 2, "栏杆": 2, "修好": 2, "太平洋": 2, "围墙": 2, "围好": 2, "一座": 2, "高铁": 2, "坐在": 2, "嫦娥": 2, "姐姐": 2, "喝酒": 2, "饮茶": 2, "安联": 2, "早": 2, "语": 2, "旁观者": 2, "难以": 2, "失联女": 2, "不幸遇难": 2, "集体": 2, "送别": 2, "受困": 2, "人口": 2, "交流": 2, "风险": 2, "部": 2, "主任": 2, "推进": 2, "交警大队": 2, "洪水": 2, "口": 2, "忙": 2, "泡": 2, "一口": 2, "津日": 2, "辣叶": 2, "摧秋": 2, "话题": 2, "甩": 2, "锅": 2, "买": 2, "常见": 2, "袭击": 2, "哈气": 2, "居住": 2, "村民": 2, "受阻": 2, "现场采访": 2, "老百姓": 2, "无聊": 2, "一幕幕": 2, "46": 2, "北部": 2, "震前": 2, "恢": 2, "周末": 2, "暂时": 2, "承诺": 2, "6666": 2, "早安": 2, "短时": 2, "持续": 2, "卫生防疫": 2, "红原县": 2, "医疗": 2, "哆": 2, "侦察": 2, "影像": 2, "桥梁": 2, "损伤": 2, "局部": 2, "嘻嘻": 2, "互联网": 2, "反": 2, "应": 2, "劈石": 2, "开路": 2, "进一步": 2, "患者": 2, "体征": 2, "平稳": 2, "头部": 2, "医生": 2, "国航": 2, "接": 2, "徒手": 2, "抬车": 2, "之": 2, "实为": 2, "地震局": 2, "晕": 2, "亿元": 2, "民政部": 2, "1500": 2, "蛋糕": 2, "黑色": 2, "办": 2, "207": 2, "轻伤": 2, "辖区": 2, "仔细": 2, "海有": 2, "联通": 2, "找": 2, "可赔": 2, "人身保险": 2, "伤害": 2, "责任保险": 2, "教": 2, "危急": 2, "悦": 2, "黄金": 2, "袭": 2, "绕行": 2, "国道": 2, "入川": 2, "首批": 2, "会诊": 2, "后续": 2, "行进": 2, "永竹": 2, "新村": 2, "免费送": 2, "情人节": 2, "领取": 2, "赣州": 2, "等待": 2, "讲述": 2, "55": 2, "探测仪": 2, "抵达": 2, "万多名": 2, "走出": 2, "一句": 2, "真": 2, "快乐": 2, "热点": 2, "节奏": 2, "允悲": 2, "开心": 2, "湖水": 2, "09": 2, "织": 2, "调集": 2, "暂": 2, "28": 2, "中断": 2, "线": 2, "通便": 2, "心系": 2, "坐": 2, "打电话": 2, "进": 2, "大队": 2, "到达": 2, "配送": 2, "面额": 2, "钞票": 2, "用于": 2, "营业网点": 2, "营业": 2, "优先": 2, "办理": 2, "延长": 2, "减灾": 2, "取暖": 2, "引": 2, "娱乐圈": 2, "暖心": 2, "Angelababy": 2, "何炅": 2, "蔡依林": 2, "宋茜": 2, "教主": 2, "盆景": 2, "发电机": 2, "奔": 2, "韩红": 2, "面对": 2, "值得": 2, "牵": 2, "战区": 2, "空军": 2, "旅": 2, "国网": 2, "供区": 2, "地震烈度": 2, "震": 2, "不": 2, "修路": 2, "修": 2, "支": 2, "医务人员": 2, "52": 2, "各方": 2, "年入": 2, "平均": 2, "2400": 2, "多万": 2, "1.1": 2, "营业额": 2, "这么久": 2, "总额": 2, "何其": 2, "男友": 2, "复合": 2, "水果": 2, "姐": 2, "用工": 2, "合同": 2, "出大招": 2, "失业": 2, "余个": 2, "工作岗位": 2, "签订": 2, "劳动合同": 2, "可": 2, "爆红": 2, "导演": 2, "兼": 2, "主角": 2, "酸": 2, "少说": 2, "作出": 2, "微薄": 2, "点亮": 2, "救助者": 2, "山上": 2, "大巴车": 2, "时刻": 2, "爸爸妈妈": 2, "护住": 2, "出车": 2, "得救": 2, "失血过多": 2, "上苍": 2, "风采": 2, "正雄": 2, "落": 2, "河沟": 2, "出": 2, "中巴车": 2, "坠河": 2, "起吊": 2, "脱离": 2, "大人": 2, "小孩": 2, "平静": 2, "痛心": 2, "多灾多难": 2, "忘怀": 2, "就定": 2, "实": 2, "轻松": 2, "午后": 2, "开盘": 2, "强势": 2, "出货": 2, "个股": 2, "百傲": 2, "化学": 2, "sh603360": 2, "仅供": 2, "喵": 2, "荷兰": 2, "声音": 2, "冠军": 2, "演绎": 2, "经典歌曲": 2, "youraisemeup": 2, "早晨": 2, "脚步": 2, "运动会": 2, "去": 2, "0909": 2, "生日快乐": 2, "请问": 2, "安排": 2, "舆情": 2, "理解": 2, "偷乐": 2, "部门": 2, "执法": 2, "部署": 2, "person": 2, "has": 2, "at": 2, "least": 2, "one": 2, "dream": 2, "消防队": 2, "长遇": 2, "鄂州": 2, "中队长": 2, "这部": 2, "破": 2, "四川省政府": 2, "新闻办": 2, "00": 2, "求": 2, "一年": 2, "农药": 2, "好吃": 2, "解放军": 2, "民兵": 2, "逝者": 2, "安息": 2, "感受一下": 2, "美的": 2, "闭上": 2, "面前": 2, "旅游景点": 2, "哈哈哈": 2, "生日": 2, "跳": 2, "动作": 2, "茂县": 2, "苍天": 2, "怜悯": 2, "武警战士": 2, "信号": 2, "时尚": 2, "铁路": 2, "透露": 2, "八方": 2, "良": 2, "难民": 2, "危房": 2, "上次": 2, "骚扰": 2, "目击者": 2, "砸伤": 2, "被单": 2, "御寒": 2, "马路": 2, "女装": 2, "微软": 2, "小冰": 2, "朱婧汐": 2, "Jing": 2, "泥石流": 2, "32": 2, "抢修": 2, "27": 2, "首度": 2, "斩获": 2, "纪录": 2, "开出": 2, "亿到": 2, "亿不等": 2, "金额": 2, "生态环境": 2, "林业": 2, "本次": 2, "相关": 2, "野外": 2, "有网": 2, "斤": 2, "工商联": 2, "华汇": 2, "置业": 2, "光彩": 2, "授牌": 2, "肃然起敬": 2, "诗人": 2, "画家": 2, "五年": 2, "裸照": 2, "走遍": 2, "全世界": 2, "ghx15952401337": 2, "清明": 2, "长假": 2, "逃兵": 2, "绑架者": 2, "主题曲": 2, "胡歌": 2, "笑话": 2, "挪车": 2, "逐月": 2, "期待": 2, "见面会": 2, "之间": 2, "短片": 2, "来时": 2, "直属": 2, "主管": 2, "298977": 2, "灭火": 2, "清障": 2, "保": 2, "一从": 2, "恐有": 2, "随即": 2, "排险": 2, "平板": 2, "厂家直销": 2, "程力": 2, "经理": 2, "年头": 2, "熟悉": 2, "熟练": 2, "需求": 2, "一辆辆": 2, "油罐车": 2, "仙童": 2, "预料": 2, "王老师": 2, "打结": 2, "形式": 2, "手上": 2, "短短的": 2, "连接起来": 2, "坚强": 2, "总代": 2, "一枚": 2, "太过": 2, "安逸": 2, "折腾": 2, "一科科": 2, "富有": 2, "只会": 2, "暴雨": 2, "佛山": 2, "嗡爷": 2, "漫画": 2, "额": 2, "女朋友": 2, "离开": 2, "备受": 2, "电": 2, "人类": 2, "曲馨秀": 2, "云梦": 2, "贝尔": 2, "包文婧": 2, "大婚": 2, "团结": 2, "十": 2, "三天": 2, "数字": 2, "浏览器": 2, "试播": 2, "开播": 2, "伤亡人数": 2, "增加": 2, "值守": 2, "客服": 2, "ht": 2, "害羞": 2, "﹏": 2, "获悉": 2, "全省": 2, "绕城": 2, "匝道": 2, "外环": 2, "货车": 2, "广甘": 2, "广元": 2, "出川": 2, "木鱼": 2, "分流": 2, "广陕": 2, "剑门关": 2, "约": 2, "我院": 2, "日前": 2, "数万": 2, "疑惑": 2, "偿还": 2, "房屋贷款": 2, "律师": 2, "逃单": 2, "返回": 2, "西安": 2, "震感": 2, "商场": 2, "果断": 2, "钟": 2, "塔影": 2, "大山深处": 2, "重灾区": 2, "301": 2, "救治": 2, "不愧": 2, "今年以来": 2, "强台风": 2, "十三号": 2, "破坏力": 2, "影响力": 2, "2017.8": 2, "打字": 2, "赶紧": 2, "习惯": 2, "奶奶": 2, "省吃俭用": 2, "件": 2, "报案": 2, "噢": 2, "侯现": 2, "光荣": 2, "救济": 2, "战士": 2, "英雄": 2, "黑": 2, "zjl0118": 2, "年底": 2, "毁坏": 2, "生机": 2, "公示": 2, "22": 2, "革命": 2, "渝": 2, "liuqinqing": 2, "最右神": 2, "浅谈": 2, "我国": 2, "收取": 2, "世": 2, "捐给": 2, "数额": 2, "楚乔传": 2, "赔不赔": 2, "统一": 2, "赔": 2, "来源": 2, "观察": 2, "凉山": 2, "平武县": 2, "Live": 2, "七年": 2, "首播": 2, "制作": 2, "JJ": 2, "全捐": 2, "精选": 2, "一张": 2, "外卖": 2, "343": 2, "人生": 2, "付出": 2, "收获": 2, "雨淇": 2, "创意": 2, "发型": 2, "玩家": 2, "游戏": 2, "探访": 2, "疮痍": 2, "并存": 2, "澎湃": 2, "决堤": 2, "双龙": 2, "芦苇": 2, "冲毁": 2, "一处": 2, "景观": 2, "桥": 2, "两侧": 2, "鲜明": 2, "一侧": 2, "污染": 2, "另一侧": 2, "原有": 2, "期间": 2, "炒作": 2, "恋情": 2, "封杀": 2, "晒": 2, "两张": 2, "电影票": 2, "呼唤": 2, "国难当头": 2, "心思": 2, "卿卿我我": 2, "达太忙": 2, "实在": 2, "帖子": 2, "难过": 2, "内容": 2, "找人": 2, "管理": 2, "不合理": 2, "整治": 2, "大雨": 2, "双": 2, "2000": 2, "张烤": 2, "馕": 2, "大叔": 2, "小熊": 2, "薰衣草": 2, "你学": 2, "好不容易": 2, "建立": 2, "一世英名": 2, "毁于一旦": 2, "良知": 2, "地球": 2, "码": 2, "醒醒": 2, "上善": 2, "尚武": 2, "挤眼": 2, "耶和华": 2, "忘": 2, "洋洋": 2, "不知": 2, "身在": 2, "箭竹": 2, "最严": 2, "海外": 2, "安置工作": 2, "帐篷": 2, "团团": 2, "捐助": 2, "天气": 2, "返程": 2, "完毕": 2, "第一次": 2, "奥": 2, "102": 2, "林场": 2, "抗洪": 2, "商家": 2, "暴涨": 2, "价格": 2, "牺牲": 2, "机器": 2, "新闻稿": 2, "作用": 2, "流连忘返": 2, "功德": 2, "贱人": 2, "啊啊啊": 2, "二哈": 2, "韩寒": 2, "刘天": 2, "部落": 2, "自由": 2, "强多": 2, "我妈": 1, "不可避免": 1, "玩吧": 1, "两场": 1, "藏": 1, "谜": 1, "衰": 1, "浪费": 1, "改为": 1, "公共": 1, "食堂": 1, "中餐厅": 1, "热播": 1, "客厅": 1, "赵薇": 1, "弄": 1, "干吗": 1, "夜里": 1, "睡": 1, "联想": 1, "哪有": 1, "母爱": 1, "心灵鸡汤": 1, "心灵": 1, "癌症": 1, "死人": 1, "特大": 1, "逝去": 1, "看法": 1, "一段话": 1, "不差": 1, "讯": 1, "关键": 1, "喊": 1, "奔跑": 1, "南充市": 1, "内部": 1, "滚落": 1, "塌方": 1, "沙石": 1, "扭曲": 1, "溪水": 1, "河南": 1, "家人": 1, "集团股份": 1, "份儿": 1, "没理由": 1, "股": 1, "电商": 1, "只想": 1, "陪": 1, "抚慰": 1, "痛": 1, "沟县": 1, "同": 1, "公安消防": 1, "命令": 1, "梯队": 1, "天水": 1, "临夏": 1, "白银": 1, "轻型": 1, "重型": 1, "新区": 1, "定西": 1, "之下": 1, "蓝": 1, "腹地": 1, "近距离": 1, "两分钟": 1, "全纪录": 1, "老虎": 1, "犀牛": 1, "湖": 1, "树正海": 1, "付费": 1, "三分钟": 1, "紧张": 1, "关键时刻": 1, "右": 1, "哼哼": 1, "用心": 1, "king": 1, "吴伟清": 1, "51619": 1, "86": 1, "西游记": 1, "经典": 1, "取景": 1, "片尾曲": 1, "路在何方": 1, "师徒": 1, "四人": 1, "走过": 1, "不复存在": 1, "晋升": 1, "奶爸": 1, "警宝": 1, "坚守": 1, "写道": 1, "请假": 1, "第四位": 1, "轰动": 1, "西瓜": 1, "交通管制": 1, "日讯": 1, "雅": 1, "安": 1, "陈月瑶": 1, "H": 1, "内功": 1, "己所不欲": 1, "勿施于人": 1, "qifei1938": 1, "领导": 1, "震塌": 1, "穷酸": 1, "京哥": 1, "拼": 1, "尽全力": 1, "换来": 1, "犹豫": 1, "赶上": 1, "慈善家": 1, "那种": 1, "城郊": 1, "阶州": 1, "评": 1, "104": 1, "博闻": 1, "天下": 1, "有理": 1, "富若": 1, "引发": 1, "争论": 1, "趋于": 1, "明朗": 1, "上风": 1, "慈善事业": 1, "不至": 1, "天宰": 1, "人祸": 1, "奖赏": 1, "迎来": 1, "2.3": 1, "8.0": 1, "坚挺": 1, "逸": 1, "居": 1, "一夜": 1, "登上": 1, "外来": 1, "61500": 1, "含": 1, "126": 1, "外国游客": 1, "23477": 1, "人失联": 1, "另有": 1, "名失": 1, "不幸身亡": 1, "一中": 1, "日才": 1, "挖出": 1, "娱圈": 1, "八妹": 1, "一晃": 1, "三年": 1, "见": 1, "嫁": 1, "没常": 1, "忘记": 1, "发给": 1, "生个": 1, "娃娃": 1, "wen": 1, "jie": 1, "I": 1, "love": 1, "you": 1, "延误": 1, "呆": 1, "岁月": 1, "静好": 1, "李连": 1, "泡面": 1, "一桶": 1, "吃住行": 1, "款": 1, "打折": 1, "勇士": 1, "营救": 1, "躲过": 1, "穿越": 1, "流沙": 1, "从镜海": 1, "狂奔": 1, "进军": 1, "日则": 1, "硬生生": 1, "解救": 1, "晚": 1, "当地人": 1, "邢先生": 1, "两个": 1, "团期": 1, "打": 1, "团费": 1, "退还": 1, "中不倒": 1, "小旗": 1, "危难": 1, "之际": 1, "举起": 1, "旗": 1, "带领": 1, "安定": 1, "雷锋": 1, "紧跟着": 1, "差点": 1, "父女": 1, "差点儿": 1, "母": 1, "不看": 1, "广告": 1, "实际行动": 1, "明智之举": 1, "烟台": 1, "世茂": 1, "之分": 1, "变相": 1, "强征": 1, "算了": 1, "每回": 1, "大灾": 1, "大难": 1, "贪腐": 1, "红眼病": 1, "摸摸": 1, "世界级": 1, "难题": 1, "众多": 1, "心情": 1, "沉痛": 1, "对象": 1, "地下": 1, "看不见": 1, "摸不着": 1, "现有": 1, "观测": 1, "间接": 1, "实验": 1, "模拟": 1, "检验": 1, "多方": 1, "搜寻": 1, "终于": 1, "今天上午": 1, "列队": 1, "多台": 1, "解围": 1, "多辆": 1, "启用": 1, "牵引": 1, "震苑": 1, "研讨会": 1, "浙江": 1, "举办": 1, "会议": 1, "围绕": 1, "实例": 1, "探讨": 1, "地震预报": 1, "蒋海昆": 1, "研究员": 1, "判断": 1, "地质学": 1, "角度看": 1, "巴颜喀拉": 1, "地块": 1, "由南向北": 1, "诱发": 1, "雨季": 1, "建议": 1, "小心": 1, "破损": 1, "房": 1, "两点": 1, "脸颊": 1, "新晋": 1, "爸爸": 1, "江油市": 1, "公安局": 1, "岳霖": 1, "执勤": 1, "午饭": 1, "间隙": 1, "聊起": 1, "谋面": 1, "48": 1, "有序": 1, "要冲": 1, "民众": 1, "恐慌": 1, "并未": 1, "一带": 1, "极乐": 1, "天才": 1, "潇洒": 1, "默默": 1, "花海": 1, "没水": 1, "雅江": 1, "断流": 1, "印度": 1, "疯狂": 1, "早班车": 1, "娼妇": 1, "迎接": 1, "退伍": 1, "拼命": 1, "刷": 1, "娘娘": 1, "贱": 1, "古代": 1, "记载": 1, "雷": 1, "民科": 1, "不胫而走": 1, "流传": 1, "最广": 1, "美誉": 1, "享有": 1, "看水": 1, "美名": 1, "第一天": 1, "人大": 1, "万名": 1, "医护人员": 1, "工人": 1, "敬": 1, "四个": 1, "寨": 1, "外界": 1, "主干道": 1, "水电": 1, "第九": 1, "支队长": 1, "丰厚": 1, "好久没": 1, "露面": 1, "欣赏": 1, "佳作": 1, "愉快": 1, "今起": 1, "关闭": 1, "旅企": 1, "退款": 1, "中青旅": 1, "600": 1, "途牛": 1, "799": 1, "9999": 1, "同程": 1, "777": 1, "7777": 1, "驴": 1, "1010": 1, "6060": 1, "携程": 1, "830": 1, "95117": 1, "扩": 1, "散": 1, "小鸟": 1, "星期五": 1, "滴滴": 1, "租车": 1, "上线": 1, "分租": 1, "试水": 1, "租赁": 1, "上海": 1, "三地": 1, "试运营": 1, "作业": 1, "专报": 1, "管理局": 1, "社区": 1, "疾控中心": 1, "安全检查": 1, "儿童": 1, "预防接种": 1, "疫苗": 1, "邛崃市": 1, "中心医院": 1, "巡诊": 1, "生活区": 1, "防疫": 1, "消毒": 1, "堂堂": 1, "政政": 1, "25957": 1, "首份": 1, "空军航空兵": 1, "某团": 1, "第一手": 1, "资料": 1, "高空": 1, "房等": 1, "裸露": 1, "几款": 1, "指尖": 1, "风": 1, "仙女们": 1, "菜": 1, "京东": 1, "腾讯": 1, "阿里巴巴": 1, "打通": 1, "区域": 1, "此刻": 1, "三名": 1, "送往": 1, "华西": 1, "诊治": 1, "63": 1, "男性": 1, "脑出血": 1, "第二位": 1, "诊断": 1, "腰椎": 1, "体": 1, "爆裂性": 1, "第三名": 1, "伤者": 1, "石头砸": 1, "颅骨": 1, "外伤性": 1, "气颅": 1, "正作": 1, "公告": 1, "去程": 1, "有无": 1, "转给": 1, "综合利用": 1, "工具": 1, "紧": 1, "IT": 1, "APP": 1, "立得": 1, "金币": 1, "换豪礼": 1, "不信谣": 1, "传谣": 1, "多地": 1, "天空": 1, "惊现": 1, "没关系": 1, "倾斜": 1, "高雄": 1, "援救": 1, "市民": 1, "征集": 1, "救助金": 1, "双倍": 1, "奉还": 1, "短信": 1, "诈骗": 1, "时期": 1, "汇总": 1, "中央财政": 1, "补助": 1, "调拨": 1, "棉帐篷": 1, "折叠床": 1, "睡袋": 1, "套": 1, "场地": 1, "照明设备": 1, "救灾物资": 1, "4.5": 1, "财政部": 1, "lvxsupreme": 1, "联名": 1, "手": 1, "红色": 1, "皮料": 1, "晚到": 1, "vx1935719228": 1, "特此": 1, "更正": 1, "年里": 1, "政治": 1, "山东": 1, "欢案": 1, "传销": 1, "更改": 1, "卡": 1, "资费": 1, "词汇": 1, "处暑": 1, "寒": 1, "来临": 1, "以人": 1, "身体": 1, "寿命": 1, "标的": 1, "定期": 1, "终身": 1, "两全": 1, "医疗保险": 1, "意外险": 1, "学校": 1, "骨科": 1, "教授": 1, "伤病": 1, "搬运": 1, "北京市": 1, "昌平区": 1, "中西医": 1, "骨伤": 1, "诊疗": 1, "潘贵": 1, "超教": 1, "互救": 1, "新闻热点": 1, "教会": 1, "熙": 1, "巢": 1, "由心": 1, "而悦": 1, "筑巢": 1, "距舟": 1, "富得流": 1, "点点": 1, "遍地": 1, "狼藉": 1, "损失估计": 1, "富": 1, "流": 1, "负担": 1, "得不到": 1, "认同": 1, "检讨": 1, "天赐": 1, "人为": 1, "示意图": 1, "处置": 1, "线图": 1, "管制": 1, "车辆通行": 1, "213": 1, "212": 1, "劝返": 1, "复线": 1, "点半": 1, "伤情": 1, "较": 1, "重": 1, "逐个": 1, "迭部": 1, "餐厅": 1, "赶到": 1, "很近": 1, "比较严重": 1, "裂缝": 1, "百姓": 1, "聊": 1, "具体情况": 1, "微博直": 1, "晓敏": 1, "施华洛": 1, "世奇": 1, "天鹅": 1, "款项": 1, "链": 1, "二维码": 1, "文字": 1, "即可": 1, "项链": 1, "颜色": 1, "自由选择": 1, "删除": 1, "福利": 1, "恋爱": 1, "协议书": 1, "品冠": 1, "victor": 1, "南亨": 1, "5.6": 1, "梦幻": 1, "聚集": 1, "疑问": 1, "奋战": 1, "调派": 1, "235": 1, "辆车": 1, "1251": 1, "已有": 1, "357": 1, "地毯式": 1, "小型": 1, "开辟": 1, "客车": 1, "瑶": 1, "随缘": 1, "话": 1, "活着": 1, "真心话": 1, "较真": 1, "确": 1, "烦恼": 1, "拿得起": 1, "放": 1, "三驾": 1, "马车": 1, "上证指数": 1, "证券": 1, "二线": 1, "资源": 1, "煤炭": 1, "有色": 1, "钢铁": 1, "品种": 1, "量": 1, "先补量": 1, "早盘": 1, "带到": 1, "3300": 1, "关口": 1, "神马": 1, "旧": 1, "宜昌": 1, "新鲜事": 1, "简单": 1, "海震": 1, "几近": 1, "干涸": 1, "深约": 1, "宽": 1, "决口": 1, "流失": 1, "露出": 1, "湖底": 1, "泥土": 1, "树根": 1, "枯木": 1, "常客": 1, "丰沛": 1, "五颜六色": 1, "33.28": 1, "103.80": 1, "3.9": 1, "中央": 1, "多支": 1, "首夜": 1, "给力": 1, "新增": 1, "K79": 1, "K83": 1, "抢通": 1, "公共交通": 1, "魔幻": 1, "早上": 1, "公交车": 1, "喷": 1, "花露水": 1, "浓到": 1, "重感冒": 1, "闻到": 1, "路上": 1, "自言自语": 1, "没戴": 1, "耳机": 1, "坐车": 1, "大爷": 1, "车上": 1, "谈论": 1, "死得": 1, "蜀黍": 1, "抬着": 1, "照相机": 1, "五星级": 1, "神仙池": 1, "消防车": 1, "客到": 1, "结束": 1, "140": 1, "泥娃娃": 1, "夏令营": 1, "龙": 1, "海涛": 1, "李金埔": 1, "谭觐": 1, "程浩": 1, "石庆玲": 1, "生火": 1, "酷": 1, "黑河": 1, "双河": 1, "安乐": 1, "最右": 1, "至漳扎": 1, "青龙桥": 1, "夜深": 1, "抓紧": 1, "共出动": 1, "396": 1, "1108": 1, "照明灯": 1, "组": 1, "33": 1, "绝症": 1, "跪求": 1, "谈不上": 1, "无奈": 1, "举": 1, "支助": 1, "理性": 1, "大于": 1, "情感": 1, "相比": 1, "要": 1, "这才": 1, "赤裸裸": 1, "报平安": 1, "最新消息": 1, "多人受": 1, "干杯": 1, "通讯": 1, "干海子": 1, "畅": 1, "亲历者": 1, "民民": 1, "飞机": 1, "国": 1, "33.12": 1, "103.87": 1, "3.7": 1, "一向": 1, "习惯于": 1, "自诩": 1, "整装待发": 1, "机动": 1, "分队": 1, "闻震而动": 1, "上报": 1, "编组": 1, "装": 1, "电力供应": 1, "585": 1, "抓住": 1, "捐款人": 1, "要脸": 1, "挣钱": 1, "进账": 1, "还给": 1, "穷死": 1, "念": 1, "点好": 1, "钱少": 1, "心愿": 1, "弘扬": 1, "财经报道": 1, "卫": 1, "计委": 1, "书面报告": 1, "卫生部门": 1, "抽排": 1, "医疗队": 1, "及州": 1, "小木": 1, "双创": 1, "商品交易": 1, "贴": 1, "环宇": 1, "智能": 1, "三只": 1, "松鼠": 1, "予七书": 1, "回收": 1, "狂欢": 1, "趴": 1, "2017.08": 1, "国产手机": 1, "报价": 1, "已破": 1, "拿到": 1, "任何人": 1, "要管": 1, "先问": 1, "补": 1, "持": 1, "用到": 1, "家财": 1, "水逆": 1, "给我发": 1, "水星": 1, "订好": 1, "缴费": 1, "告知": 1, "南航": 1, "程票": 1, "有感": 1, "雅居观": 1, "剧销": 1, "酷暑": 1, "楼宇": 1, "摇晃": 1, "惊魂": 1, "蜂拥": 1, "而出": 1, "潮水": 1, "众语": 1, "喧哗": 1, "探": 1, "传来": 1, "人皆叹": 1, "毁容": 1, "人疑": 1, "三峡": 1, "祸患": 1, "要闻": 1, "回顾": 1, "TFBOYS": 1, "艾薇儿": 1, "神秘": 1, "男": 1, "上街": 1, "变小": 1, "艾": 1, "奥兰多": 1, "同框": 1, "孙莉": 1, "俩": 1, "小伙": 1, "急": 1, "回家": 1, "起纠纷": 1, "警调": 1, "衔接": 1, "化解": 1, "台币": 1, "正面": 1, "善": 1, "香港": 1, "近几年": 1, "原因": 1, "vx": 1, "L": 1, "贴纸": 1, "打卡": 1, "1131878423": 1, "fade": 1, "我订": 1, "好友": 1, "发来": 1, "发生意外": 1, "隐患": 1, "e244": 1, "鬼斧神工": 1, "更好": 1, "梦寐以求": 1, "驾驶": 1, "三部": 1, "星夜": 1, "兼程": 1, "长途": 1, "行驶": 1, "山路": 1, "崎岖": 1, "恶劣": 1, "老化": 1, "家居": 1, "面临": 1, "老王": 1, "爆料": 1, "吐槽": 1, "曝料": 1, "玫瑰": 1, "杜甫": 1, "爱豆": 1, "应援": 1, "步": 1, "运动": 1, "教室": 1, "答": 1, "299nWN": 1, "6wd": 1, "DW": 1, "w": 1, "发了": 1, "宽频网": 1, "舔": 1, "屏": 1, "互粉": 1, "艺兴": 1, "霸屏": 1, "羊毛": 1, "天微博": 1, "打不开": 1, "好像": 1, "突发事件": 1, "舆论": 1, "小组": 1, "介入": 1, "一大": 1, "例子": 1, "减少": 1, "官话": 1, "各种渠道": 1, "展现": 1, "喜": 1, "普": 1, "涅": 1, "磐": 1, "重生": 1, "一刹那": 1, "眼泪": 1, "止不住": 1, "流下来": 1, "始终": 1, "我行我素": 1, "行事": 1, "作风": 1, "一拳": 1, "重击": 1, "给人以": 1, "惊喜": 1, "老板": 1, "感言": 1, "有时候": 1, "多年": 1, "两万": 1, "搬弄是非": 1, "摸": 1, "转需": 1, "后成": 1, "灌": 1, "成温": 1, "邛": 1, "彭": 1, "城北": 1, "出口": 1, "设立": 1, "车道": 1, "保畅": 1, "客运": 1, "全员": 1, "准备就绪": 1, "反对": 1, "他边": 1, "嫉妒": 1, "吴京狂": 1, "十几亿": 1, "当初": 1, "情牵": 1, "525": 1, "抢险救灾": 1, "彰显": 1, "责任": 1, "拜托": 1, "小伙伴": 1, "儿们": 1, "上万斤": 1, "处于": 1, "滞销": 1, "状态": 1, "亲们": 1, "帮帮忙": 1, "解决": 1, "成果": 1, "纯天然": 1, "多水脆": 1, "甜": 1, "现摘": 1, "现寄": 1, "河神": 1, "西城": 1, "男孩": 1, "告别": 1, "YOURAISEMEUP": 1, "遇到困难": 1, "各大": 1, "生": 1, "图强": 1, "这绝": 1, "学车": 1, "教练": 1, "太太": 1, "反感": 1, "盘问": 1, "来练车": 1, "老太太": 1, "送死": 1, "麻烦": 1, "张嘴": 1, "拜": 1, "钢琴": 1, "女童": 1, "脆弱": 1, "愿生者": 1, "制": 1, "救援车": 1, "关注度": 1, "比不上": 1, "打喷嚏": 1, "悲剧": 1, "减肥操": 1, "大": 1, "盯": 1, "一遍": 1, "中石化": 1, "分公司": 1, "立即行动": 1, "加油站": 1, "随到": 1, "随加": 1, "必经": 1, "设置": 1, "易捷": 1, "卓玛泉": 1, "开水": 1, "aaa752": 1, "咖啡": 1, "防": 1, "床": 1, "兄弟": 1, "悲": 1, "催": 1, "昏迷": 1, "民工": 1, "杨": 1, "长安": 1, "工地": 1, "劳作": 1, "一堵": 1, "木制": 1, "墙": 1, "连喊": 1, "担架": 1, "影视娱乐": 1, "澄": 1, "旧爱": 1, "吴京怒": 1, "怼": 1, "无脑": 1, "提问": 1, "快手": 1, "浪子": 1, "磊少": 1, "语录": 1, "双击": 1, "势力": 1, "榜": 1, "视频秀": 1, "619382072": 1, "加勒比海": 1, "乌篷船": 1, "大牌": 1, "潮流": 1, "太阳眼镜": 1, "墨镜": 1, "代购": 1, "8.23": 1, "带": 1, "心存": 1, "力所能及": 1, "便是": 1, "保佑": 1, "受难": 1, "意义": 1, "忧虑": 1, "力": 1, "於": 1, "预防": 1, "到位": 1, "後": 1, "倒灌": 1, "四处": 1, "飘散": 1, "水浸": 1, "独居": 1, "老人": 1, "二十个": 1, "无情": 1, "人间": 1, "有情": 1, "关": 1, "粉": 1, "九亿": 1, "妓女": 1, "遭天": 1, "谴": 1, "牵连": 1, "美如画": 1, "大地": 1, "博主": 1, "文案": 1, "水平": 1, "写稿": 1, "十分之一": 1, "善良": 1, "那天": 1, "懂得": 1, "同情": 1, "诬陷": 1, "水滴": 1, "河北": 1, "邢台": 1, "31": 1, "危及": 1, "抢救": 1, "重症": 1, "监护室": 1, "ICU": 1, "病房": 1, "三个": 1, "截肢": 1, "后期": 1, "脱离危险": 1, "花费": 1, "三十多万": 1, "满地": 1, "瓦片": 1, "死守": 1, "劝离": 1, "新京": 1, "老子": 1, "一分": 1, "门票费": 1, "纳税人": 1, "手里": 1, "扣来": 1, "钱作": 1, "补贴": 1, "贪污": 1, "不明": 1, "事理": 1, "骗人": 1, "混蛋": 1, "她家": 1, "买美瞳": 1, "款式": 1, "姐妹": 1, "特意": 1, "关心": 1, "快去": 1, "资阳": 1, "雁江": 1, "窗玻璃": 1, "破碎": 1, "披": 1, "点火": 1, "据漳扎": 1, "烂": 1, "垮": 1, "玻璃": 1, "二楼": 1, "显示": 1, "过夜": 1, "身披": 1, "起火": 1, "用手": 1, "捂着": 1, "头": 1, "岛国": 1, "一小": 1, "下馆子": 1, "好奇": 1, "乌贼": 1, "盖饭": 1, "食欲": 1, "堪称": 1, "减肥": 1, "必备": 1, "诚实": 1, "__": 1, "一善": 1, "总在": 1, "风雨": 1, "包邮": 1, "韩版": 1, "领": 1, "碎花": 1, "中长款": 1, "女": 1, "裙子": 1, "长袖": 1, "衬衫": 1, "连衣裙": 1, "新款": 1, "特首": 1, "道歉": 1, "局长": 1, "辞职": 1, "万人": 1, "196": 1, "舟曲": 1, "1557": 1, "央企调": 1, "美心": 1, "系列产品": 1, "400ml": 1, "高端": 1, "Gucci": 1, "香水": 1, "沐浴露": 1, "情书": 1, "圆明园": 1, "中国联通": 1, "用户": 1, "停机": 1, "联通公司": 1, "117": 1, "基站": 1, "抢险车": 1, "35": 1, "阻拦": 1, "非哥": 1, "HOT": 1, "税": 1, "1200": 1, "主持": 1, "会上": 1, "副厅长": 1, "宾军宜": 1, "地处": 1, "玉能": 1, "一对": 1, "戴玉": 1, "母子": 1, "情怀": 1, "地位": 1, "玉集": 1, "阴阳": 1, "二气": 1, "精纯": 1, "天性": 1, "抛弃": 1, "愈久": 1, "愈美": 1, "传家之宝": 1, "传承": 1, "公爵": 1, "385": 1, "净水器": 1, "生产厂家": 1, "批发": 1, "关爱": 1, "水质": 1, "停车": 1, "场": 1, "伊瘦": 1, "酵素": 1, "奶昔": 1, "吃货": 1, "拥有": 1, "好身材": 1, "冲泡": 1, "喝一杯": 1, "完美": 1, "蜕变": 1, "曲线": 1, "秀": 1, "but": 1, "陈奕迅": 1, "羌族": 1, "自治县": 1, "授予": 1, "执委": 1, "绵阳市": 1, "事业": 1, "先进": 1, "荣誉称号": 1, "人民政府": 1, "副县长": 1, "主席": 1, "谢普": 1, "仪式": 1, "谢普说": 1, "自觉": 1, "践行": 1, "精神": 1, "推崇": 1, "挖掘出": 1, "第五": 1, "具": 1, "消防队员": 1, "中国青年报": 1, "囧": 1, "严阵": 1, "连阳": 1, "SUNT": 1, "SUNTV": 1, "鸡毛": 1, "水彩": 1, "习作": 1, "片": 1, "肃然": 1, "德国": 1, "直邮": 1, "biotulin": 1, "精华": 1, "到货": 1, "拆箱": 1, "星期二": 1, "陶喆": 1, "美妆": 1, "交通堵塞": 1, "剧组": 1, "黑粉": 1, "泰": 1, "友谊": 1, "应对": 1, "大国": 1, "东京": 1, "做些": 1, "许昌": 1, "搜索": 1, "直": 1, "洒水车": 1, "随车": 1, "13597840021": 1, "菲菲": 1, "191437020": 1, "品牌": 1, "创始人": 1, "爱捐": 1, "不服": 1, "无耻": 1, "编自": 1, "西子": 1, "丹": 1, "67": 1, "湖南": 1, "水灾": 1, "一毛": 1, "桶": 1, "白开水": 1, "杯": 1, "老天爷": 1, "赐予": 1, "看得见": 1, "戏": 1, "今晨": 1, "震中区": 1, "一切顺利": 1, "一首": 1, "祝你平安": 1, "张蕾": 1, "粉丝团": 1, "挣": 1, "卖命": 1, "赚来": 1, "失败": 1, "倾家荡产": 1, "旁边": 1, "看笑话": 1, "意愿": 1, "三五千": 1, "捐个": 1, "几毛钱": 1, "坑": 1, "爹": 1, "吹": 1, "认得": 1, "打球": 1, "天说": 1, "大良": 1, "狗蛋": 1, "风水": 1, "命理": 1, "平时": 1, "摔": 1, "男朋友": 1, "lei993": 1, "防震": 1, "7.1": 1, "羌活": 1, "沟经": 1, "大路": 1, "乡到": 1, "若尔盖": 1, "人烟稀少": 1, "沟口": 1, "第四天": 1, "世间": 1, "沈阳": 1, "北陵": 1, "陷入": 1, "漩涡": 1, "发微博": 1, "名义": 1, "木结构": 1, "抗震": 1, "众所周知": 1, "现象": 1, "轻微": 1, "不易": 1, "察觉": 1, "华夏": 1, "之音": 1, "纯中药": 1, "瘦身": 1, "胶囊": 1, "一瓶": 1, "丸子": 1, "效果": 1, "辣": 1, "牛": 1, "吴昕": 1, "首谈": 1, "风波": 1, "吴京首": 1, "谈": 1, "高校学生": 1, "献唱": 1, "一串串": 1, "四川大学": 1, "所": 1, "高校": 1, "献": 1, "唱歌曲": 1, "奇秀": 1, "招": 1, "爱奇艺": 1, "旗下": 1, "平台": 1, "人流量": 1, "刷量": 1, "底薪": 1, "有意者": 1, "拖欠工资": 1, "谱": 1, "宝宝": 1, "私信": 1, "135": 1, "卫生": 1, "军队": 1, "出动": 1, "彻夜进行": 1, "乌鲁木齐": 1, "余震不断": 1, "忙碌": 1, "街": 1, "邯郸": 1, "前天": 1, "这": 1, "中奖": 1, "玛薇丝": 1, "万齐克": 1, "出面": 1, "独": 1, "7.587": 1, "亿美元": 1, "51": 1, "威力": 1, "球": 1, "头彩": 1, "奖金": 1, "万齐克称": 1, "医学中心": 1, "回去": 1, "骗": 1, "彩票": 1, "测绘": 1, "地理信息": 1, "党委书记": 1, "赵": 1, "继成": 1, "分管": 1, "院长": 1, "刘纪平": 1, "科技成果": 1, "推广": 1, "院属": 1, "婊": 1, "恶心": 1, "买房人": 1, "还贷": 1, "主合同": 1, "借贷": 1, "餐饮": 1, "用餐": 1, "餐馆": 1, "强求": 1, "多位": 1, "真心": 1, "遇险": 1, "逃": 1, "遇车": 1, "灾损": 1, "1680": 1, "损坏": 1, "1037": 1, "轻度": 1, "420": 1, "中度": 1, "223": 1, "重度": 1, "共有": 1, "规划": 1, "叠加": 1, "八级": 1, "烈度": 1, "内有": 1, "九级": 1, "碧": 1, "突击队": 1, "就医": 1, "警察": 1, "增援": 1, "属地": 1, "消防大队": 1, "沿线": 1, "握手": 1, "转送": 1, "堵": 1, "塞": 1, "勘": 1, "余伤": 1, "最让人": 1, "保命": 1, "超": 1, "实用": 1, "务必": 1, "数百人": 1, "标准": 1, "求生": 1, "姿势": 1, "家里": 1, "常备": 1, "万全": 1, "抵挡": 1, "无常": 1, "lt": 1, "切克": 1, "闹": 1, "有天": 1, "王者": 1, "一半": 1, "一妹": 1, "纸": 1, "握草": 1, "ps": 1, "杜撰": 1, "劝": 1, "那妹": 1, "纸来": 1, "句": 1, "早就": 1, "小震": 1, "死不了": 1, "跑不了": 1, "愣": 1, "干": 1, "打龙": 1, "射手": 1, "出破甲": 1, "肉": 1, "ad": 1, "穿破": 1, "衣": 1, "十几万": 1, "威海": 1, "邢威敏": 1, "用卖": 1, "学生": 1, "贫困山区": 1, "捐资助学": 1, "毫不犹豫": 1, "忧心": 1, "一共": 1, "295": 1, "赔付": 1, "257": 1, "万左右": 1, "人均": 1, "做错": 1, "源自": 1, "果不其然": 1, "准时": 1, "假期作业": 1, "卵": 1, "人民币": 1, "...#": 1, "ETNEWS": 1, "报导": 1, "小小": 1, "栀子花": 1, "想换": 1, "手机号": 1, "感情": 1, "但特": 1, "不给力": 1, "干扰": 1, "4G": 1, "久": 1, "联网": 1, "大姐": 1, "电信": 1, "正好": 1, "借换": 1, "躲开": 1, "亿万": 1, "闻讯": 1, "发坐": 1, "所到之处": 1, "敬重": 1, "大爱之举": 1, "临泉": 1, "骄傲": 1, "凯旋归来": 1, "镇党委": 1, "热烈欢迎": 1, "心安": 1, "作者": 1, "张洪泉": 1, "家财万贯": 1, "号召": 1, "首位": 1, "客户端": 1, "精彩": 1, "创译": 1, "su": 1, "aman021": 1, "我过": 1, "奢求": 1, "身上": 1, "无父": 1, "无母": 1, "孤儿": 1, "整天": 1, "挣来": 1, "亿万富翁": 1, "实力": 1, "江源": 1, "一年一度": 1, "七夕节": 1, "盘点": 1, "好久不见": 1, "全季": 1, "海底": 1, "捞": 1, "海景房": 1, "打算": 1, "韩国": 1, "李准": 1, "基": 1, "分手": 1, "王美娟": 1, "挥": 1, "屠刀": 1, "会救": 1, "虐待": 1, "丢弃": 1, "想过": 1, "动物": 1, "发声": 1, "宝贝": 1, "涂涂": 1, "tuyoulian": 1, "南庄": 1, "108": 1, "分布": 1, "余公里": 1, "山沟": 1, "婉如": 1, "色彩斑斓": 1, "陶醉": 1, "本组": 1, "微博上": 1, "地域": 1, "费解": 1, "难听": 1, "刷牙": 1, "气": 1, "不用": 1, "嘴巴": 1, "十四": 1, "5104.246385": 1, "天翔": 1, "法": 1, "现将": 1, "资金": 1, "予以": 1, "淮南市": 1, "97": 1, "党员": 1, "捐赠者": 1, "王秀忠": 1, "溘然长逝": 1, "临终": 1, "留下": 1, "遗嘱": 1, "托付": 1, "儿女": 1, "代他": 1, "1000": 1, "王老": 1, "自幼": 1, "历经": 1, "无数次": 1, "洗礼": 1, "生死考验": 1, "负伤": 1, "体内": 1, "留有": 1, "弹片": 1, "一生": 1, "离休": 1, "困难群众": 1, "毫无疑问": 1, "名利双收": 1, "巨额": 1, "理由": 1, "捐过": 1, "不难理解": 1, "须": 1, "征得": 1, "高新区": 1, "科技局": 1, "莫名": 1, "宠物": 1, "卖萌": 1, "800": 1, "青海": 1, "可恨": 1, "东莞": 1, "袁屋": 1, "遗产地": 1, "经济学": 1, "法律依据": 1, "业者": 1, "告白": 1, "过问": 1, "死活": 1, "多钱": 1, "没拿到": 1, "藏族": 1, "羌": 1, "收益": 1, "比较慢": 1, "想不通": 1, "流行": 1, "每次": 1, "尊重": 1, "人物": 1, "热议": 1, "有没有": 1, "事件": 1, "折射出": 1, "病态": 1, "仇富": 1, "心理": 1, "斤斤计较": 1, "目光": 1, "投向": 1, "开启": 1, "新老": 1, "络绎不绝": 1, "美眉": 1, "价": 1, "一盒": 1, "代言": 1, "德芙": 1, "承包": 1, "夏天": 1, "情在": 1, "表演": 1, "情景剧": 1, "系": 1, "圈里": 1, "伤亡": 1, "B": 1, "太平": 1, "百万": 1, "无忧": 1, "仅交": 1, "保费": 1, "1670": 1, "年保": 1, "储蓄型": 1, "这笔": 1, "留": 1, "十八名": 1, "中学": 1, "休整": 1, "犬刚": 1, "普格县": 1, "女生": 1, "总说": 1, "将来": 1, "一拖再拖": 1, "上天": 1, "收回": 1, "追逐": 1, "不见": 1, "一百个": 1, "荔枝": 1, "我大": 1, "够": 1, "小榄": 1, "心痛": 1, "悄悄": 1, "毁损": 1, "模样": 1, "碎": 1, "痛快": 1, "有刷": 1, "入": 1, "网红": 1, "人求": 1, "影院": 1, "Flipboard": 1, "仿若": 1, "本周": 1, "港澳": 1, "粤": 1, "特朗普": 1, "增兵": 1, "阿富汗": 1, "饿": 1, "收购": 1, "百度": 1, "打响": 1, "美团": 1, "决战": 1, "全球": 1, "iPhone": 1, "消息人士": 1, "去勇": 1, "少女": 1, "传奇": 1, "今生": 1, "红樱桃": 1, "唇膏": 1, "查明": 1, "危重": 1, "断": 1, "如骑": 1, "用力": 1, "蹬": 1, "一路上": 1, "逆风": 1, "顺风": 1, "取决于": 1, "嘴唇": 1, "PentaQ": 1, "刺猬": 1, "竞社": 1, "有个": 1, "挂机": 1, "顶上": 1, "出处": 1, "联盟": 1, "上传": 1, "聊天": 1, "截图": 1, "队友": 1, "要紧": 1, "举报": 1, "讨厌": 1, "心意": 1, "两三个": 1, "亿比": 1, "瞎": 1, "掰掰": 1, "吴京因": 1, "遭逼": 1, "专访": 1, "何润锋": 1, "两次": 1, "41": 1, "33.18": 1, "103.85": 1, "3.3": 1, "左腰": 1, "划出": 1, "一道": 1, "口子": 1, "五月": 1, "科学网": 1, "太阳活动": 1, "记录": 1, "我要": 1, "网站": 1, "天文学": 1, "宇宙学": 1, "弱": 1, "日夜": 1, "颠倒": 1, "时间段": 1, "我能": 1, "感知": 1, "YOUNG": 1, "后援会": 1, "官博": 1, "初二": 1, "那年": 1, "转校": 1, "班": 1, "一万个": 1, "忧愁": 1, "欢喜": 1, "庆幸": 1, "伴随": 1, "四周": 1, "山石": 1, "路面": 1, "公路": 1, "进山": 1, "向诺": 1, "日朗": 1, "意中人": 1, "盖世英雄": 1, "他会": 1, "踩": 1, "七色": 1, "云彩": 1, "娶": 1, "彩云": 1, "猜中": 1, "前头": 1, "猜不着": 1, "结局": 1, "父辈": 1, "饭局": 1, "大伯": 1, "开业": 1, "一周": 1, "点多": 1, "停后": 1, "上空": 1, "烟雨": 1, "缭绕": 1, "群山": 1, "衬托": 1, "呈现": 1, "两轮": 1, "愿望": 1, "心爱": 1, "一睹": 1, "秋天": 1, "那场": 1, "改变": 1, "日思夜想": 1, "爱车": 1, "算": 1, "填补": 1, "男孩儿": 1, "好样": 1, "挺住": 1, "旋律": 1, "震撼": 1, "反战": 1, "歌者": 1, "呐喊": 1, "打动": 1, "献给": 1, "止住": 1, "恒苏": 1, "华天": 1, "憾": 1, "私心": 1, "攻略": 1, "奇葩": 1, "终极": 1, "送到": 1, "烤肉店": 1, "华西都市报": 1, "同城会": 1, "成都旅游": 1, "官微": 1, "牙尖": 1, "痕迹": 1, "牧场": 1, "甘海子": 1, "一段": 1, "打广告": 1, "第一张": 1, "川主寺": 1, "镇上": 1, "庄园": 1, "各位朋友": 1, "山里": 1, "产品": 1, "零售价": 1, "128": 1, "批发价": 1, "必看": 1, "买房": 1, "地名": 1, "粤语": 1, "扣": 1, "狗刨": 1, "资讯": 1, "众人": 1, "赏赐": 1, "看吧": 1, "生存主义": 1, "中新网": 1, "日电": 1, "王鹏": 1, "不吃": 1, "倒": 1, "吐": 1, "流利地": 1, "说出": 1, "绕口令": 1, "在场": 1, "笑了起来": 1, "阅读": 1, "cn": 1, "给钱": 1, "游": 1, "绝版": 1, "生死": 1, "灿烂": 1, "高万泰": 1, "博客": 1, "师范": 1, "天旋地转": 1, "附": 1, "闪烁着": 1, "一两点": 1, "灯光": 1, "黑漆": 1, "真是太": 1, "蓝绿": 1, "相间": 1, "晶莹剔透": 1, "难忘": 1, "复原": 1, "俄罗斯": 1, "民族": 1, "文化": 1, "壮游": 1, "井然有序": 1, "社交": 1, "媒体": 1, "分社": 1, "现示": 1, "搭建": 1, "看微博": 1, "后知后觉": 1, "万幸": 1, "温暖": 1, "军民": 1, "石条": 1, "左侧": 1, "颞部": 1, "粉碎性": 1, "失语症": 1, "状": 1, "转运": 1, "图为": 1, "树正": 1, "群海": 1, "两": 1, "宁泽涛": 1, "全运会": 1, "倒计时": 1, "七天": 1, "好消息": 1, "包粉": 1, "共": 1, "为": 1, "中国扶贫基金会": 1, "发起": 1, "4774.5": 1, "前线": 1, "包粉们": 1, "P": 1, "S": 1, "发票": 1, "开取": 1, "炎热": 1, "着装": 1, "肥皂": 1, "平": 1, "武林": 1, "家坝": 1, "开导": 1, "第一批": 1, "驶离": 1, "严阵以待": 1, "交接": 1, "护送": 1, "好多": 1, "复制": 1, "永康": 1, "3.5": 1, "预计": 1, "时前": 1, "初步统计": 1, "35000": 1, "旅行团": 1, "自驾游": 1, "陆续": 1, "统一安排": 1, "蓝天白云": 1, "山清水秀": 1, "毁掉": 1, "顺便": 1, "人士": 1, "返家": 1, "闭嘴": 1, "重伤员": 1, "国防": 1, "早间": 1, "提高": 1, "生存率": 1, "冲向": 1, "电梯": 1, "窗户": 1, "躲": 1, "桌子": 1, "户外": 1, "电线杆": 1, "树": 1, "建筑物": 1, "高架桥": 1, "靠边": 1, "时要": 1, "冷静": 1, "温馨": 1, "因受": 1, "近几天": 1, "小雨": 1, "大到暴雨": 1, "乱跑": 1, "雨具": 1, "充电": 1, "宝": 1, "贺涵": 1, "张俪": 1, "上古": 1, "情歌": 1, "双世": 1, "王妃": 1, "0605": 1, "护肤": 1, "白百何": 1, "曝": 1, "出轨": 1, "微微": 1, "困难": 1, "无论是": 1, "98": 1, "防汛": 1, "后美": 1, "狠黑": 1, "遭": 1, "痛宰": 1, "Z": 1, "社": 1, "X": 1, "主义": 1, "乘火打劫": 1, "同济": 1, "博士生": 1, "扫": 1, "╭": 1, "╮": 1, "帅哥": 1, "长高": 1, "㎝": 1, "╰": 1, "╯": 1, "功夫不负有心人": 1, "回报": 1, "白敬亭": 1, "顾南衣": 1, "瞧瞧": 1, "娟": 1, "白水": 1, "厦门": 1, "买车": 1, "天": 1, "6000": 1, "人捐": 1, "42": 1, "真相": 1, "感动": 1, "队员": 1, "集合": 1, "驾车": 1, "厦": 1, "只知": 1, "大势": 1, "已来": 1, "凯迪": 1, "点击": 1, "小青年": 1, "唯独": 1, "幸灾乐祸": 1, "容不得": 1, "车技": 1, "绿": 1, "丝带": 1, "草泥马": 1, "互助": 1, "相继": 1, "生存": 1, "惊慌失措": 1, "08.24": 1, "甲申": 1, "闰": 1, "07.03": 1, "皈依": 1, "三宝": 1, "心印妙经": 1, "感应": 1, "志心": 1, "皈命": 1, "礼": 1, "寻声": 1, "感太乙": 1, "救苦": 1, "天尊": 1, "15041": 1, "以此": 1, "普及": 1, "诵经": 1, "保平安": 1, "消灾": 1, "增": 1, "福寿": 1, "当日": 1, "所行持": 1, "善法": 1, "无量": 1, "众生": 1, "亲近": 1, "正法": 1, "斋主": 1, "丁酉": 1, "大吉": 1, "愿慈": 1, "个性": 1, "搭配": 1, "昭通": 1, "犬队": 1, "待命": 1, "时节": 1, "童话": 1, "怡人": 1, "翠花": 1, "336699": 1, "内涵": 1, "厅长": 1, "法制": 1, "微评": 1, "最见": 1, "浮云": 1, "推车": 1, "馋嘴": 1, "马云": 1, "三十年": 1, "稿件": 1, "用词": 1, "准确": 1, "行文流畅": 1, "地形": 1, "面面俱到": 1, "临阵": 1, "受命": 1, "成品": 1, "不过如此": 1, "反邪教": 1, "原创": 1, "系列": 1, "日期": 1, "老婆": 1, "622": 1, "减脂": 1, "食谱": 1, "无心": 1, "法师": 1, "秦时": 1, "明月": 1, "丽人": 1, "心之迪丽": 1, "热巴": 1, "人民日报": 1, "养生": 1, "时报": 1, "卫视": 1, "养生堂": 1, "一举一动": 1, "当天": 1, "上映": 1, "突破": 1}