{"爱": 539, "地震": 354, "九寨沟": 345, "四川": 167, "旅行": 142, "摄影": 133, "搞笑": 132, "生活": 130, "救援": 81, "发生": 61, "祈福": 42, "消防": 40, "灾区": 40, "旅游": 38, "平武": 38, "游客": 32, "第一": 31, "车": 29, "时间": 28, "遇难者": 27, "返程": 24, "境内": 24, "废墟": 22, "找到": 22, "一名": 22, "现场": 21, "千古": 21, "公安": 20, "遗体": 20, "逃生": 20, "蜡烛": 20, "中国": 20, "前往": 19, "昨晚": 18, "孩子": 18, "央企": 18, "应急": 18, "组织": 18, "车辆": 18, "新疆": 18, "平安": 18, "航拍": 18, "恢复": 17, "官兵": 17, "做": 17, "生命": 17, "摄影师": 17, "情": 17, "受伤": 16, "交警大队": 16, "江油": 16, "观众": 16, "特效": 16, "希望": 16, "景区": 15, "雅安": 14, "队伍": 14, "顺利": 14, "阿坝": 14, "人员": 14, "撤离": 14, "危险": 14, "温暖": 14, "搜救": 14, "震区": 14, "震中": 14, "几个": 13, "支队": 13, "演艺": 13, "中队": 12, "加油": 12, "背后": 12, "多家": 12, "通信": 12, "开通": 12, "抢险": 12, "骨折": 12, "贪便宜": 12, "南充": 12, "砸": 12, "抢修": 12, "辆": 12, "平": 12, "武林": 12, "家坝": 12, "路段": 12, "开导": 12, "统一": 12, "引导": 12, "确保": 12, "受困": 12, "通行": 12, "第一批": 12, "驶离": 12, "交警": 12, "严阵以待": 12, "交接": 12, "护送": 12, "汶川": 12, "太": 12, "情景剧": 12, "跑": 12, "正确": 12, "震后": 12, "声音": 12, "第一个": 12, "被困": 12, "陈勇": 12, "宜宾": 12, "驾驶员": 12, "喵": 12, "阿坝州": 11, "路": 10, "罗川": 10, "滨": 10, "免": 10, "志愿者": 10, "壹": 10, "救灾": 10, "技巧": 10, "演出": 10, "台上": 10, "演员": 10, "台下": 10, "逝者": 10, "安息": 10, "珍惜": 10, "风景": 10, "不幸": 10, "武警": 10, "军人": 10, "想": 9, "日晚": 9, "依然": 9, "总队": 9, "凌晨": 9, "无人机": 9, "人间天堂": 9, "有多美": 9, "告诉": 9, "鄂州": 8, "副": 8, "中队长": 8, "所有人": 8, "酒店": 8, "黄龙": 8, "供电": 8, "害怕": 8, "伤害": 8, "一辆": 8, "报团": 8, "赴": 8, "天气": 8, "赞": 8, "南京": 8, "民间": 8, "团体": 8, "余震不断": 8, "乡": 8, "发放": 8, "视频": 8, "风景区": 8, "奶奶": 8, "脆弱": 8, "确认": 8, "发现": 8, "明星": 8, "最美": 8, "直升机": 8, "飞行": 8, "抵达": 8, "天堂": 8, "避难": 8, "新": 8, "路上": 7, "失望": 7, "遇": 7, "受损": 7, "今晨": 7, "部队": 7, "中心": 7, "美丽": 7, "度假": 6, "喊话": 6, "转移": 6, "背影": 6, "祖国": 6, "电力企业": 6, "寻亲": 6, "热线": 6, "石油": 6, "石化": 6, "绿色通道": 6, "备足": 6, "库存": 6, "调集": 6, "事件": 6, "大妈": 6, "感慨": 6, "惹祸": 6, "大巴": 6, "巨石": 6, "死": 6, "伤": 6, "岁任": 6, "女士": 6, "双腿": 6, "爆炸": 6, "玩": 6, "事儿": 6, "餐馆老板": 6, "报": 6, "中国联通": 6, "用户": 6, "提供": 6, "停机": 6, "服务": 6, "联通": 6, "联通公司": 6, "支": 6, "基站": 6, "抢险车": 6, "台": 6, "发电机": 6, "丽江": 6, "一家": 6, "机场": 6, "忙碌": 6, "基金": 6, "大录": 6, "徒步": 6, "落石": 6, "灾情": 6, "安好": 6, "队": 6, "冰棍": 6, "目击者": 6, "称": 6, "表演": 6, "首批": 6, "关注": 6, "方法": 6, "错误": 6, "带来": 6, "秋天": 6, "消息": 6, "疏导": 6, "起飞": 6, "奔赴": 6, "山体": 6, "滑坡": 6, "力量": 6, "天佑": 6, "有人": 6, "一件": 6, "景观": 6, "同意": 6, "途中": 6, "话筒": 6, "妻女": 6, "陈先生": 6, "群众": 6, "火花": 6, "巴中": 6, "包": 6, "顶": 5, "当地人": 5, "两个": 5, "休假": 4, "消防队": 4, "长遇": 4, "停车场": 4, "躲避": 4, "下午": 4, "两点": 4, "对不起": 4, "亲吻": 4, "脸颊": 4, "新晋": 4, "爸爸": 4, "江油市": 4, "公安局": 4, "辅警": 4, "岳霖": 4, "执勤": 4, "午饭": 4, "间隙": 4, "聊起": 4, "未": 4, "谋面": 4, "麦当劳": 4, "人心": 4, "本来": 4, "同": 4, "送面": 4, "饿": 4, "一夜": 4, "做好": 4, "握手": 4, "结伴": 4, "寻找": 4, "失联": 4, "三口": 4, "快报": 4, "记者": 4, "禄口": 4, "偶遇": 4, "位": 4, "曙光": 4, "此前": 4, "参与": 4, "王刚": 4, "安徽": 4, "开会": 4, "明月": 4, "青天": 4, "众星": 4, "消防员": 4, "物资": 4, "临时": 4, "取消": 4, "钱": 4, "号": 4, "正": 4, "村里": 4, "家人": 4, "队员": 4, "赶赴": 4, "道路": 4, "头条": 4, "织": 4, "牵动": 4, "一方有难": 4, "八方支援": 4, "震中区": 4, "同胞": 4, "一切顺利": 4, "一首": 4, "祝你平安": 4, "张蕾": 4, "粉丝团": 4, "情况": 4, "陇南": 4, "核实": 4, "梯队": 4, "兰州": 4, "重型": 4, "舞台剧": 4, "火速": 4, "十八": 4, "威海": 4, "新闻": 4, "岁": 4, "女性": 4, "照相机": 4, "死亡": 4, "暂": 4, "处": 4, "转发": 4, "众": 4, "引": 4, "社会": 4, "娱乐圈": 4, "暖心": 4, "吴京": 4, "黄晓明": 4, "何炅": 4, "蔡依林": 4, "赵丽颖": 4, "宋茜": 4, "圈": 4, "教主": 4, "思考": 4, "荷兰": 4, "冠军": 4, "演绎": 4, "经典歌曲": 4, "发出": 4, "全国": 4, "早晨": 4, "真的": 4, "西林": 4, "凤腾": 4, "通航": 4, "空中客车": 4, "广汉": 4, "航空": 4, "物语": 4, "围观": 4, "发表": 4, "博文": 4, "远离": 4, "官": 4, "漳扎镇": 4, "开心": 4, "林俊杰": 4, "版": 4, "听到": 4, "彻夜未眠": 4, "埋": 4, "截止": 4, "到达": 4, "洲际": 4, "大饭店": 4, "安然": 4, "入睡": 4, "地方": 4, "好人": 4, "榜": 4, "发布": 4, "宜宾市": 4, "陈勇点": 4, "川": 4, "戎通": 4, "运输": 4, "有限公司": 4, "翠屏": 4, "分公司": 4, "驾驶": 4, "大巴车": 4, "行驶": 4, "情景": 4, "区": 4, "瞬间": 4, "情况紧急": 4, "点赞": 4, "比赛": 4, "结束": 4, "日本": 4, "灾后": 4, "宣传片": 4, "看一看": 4, "节电池": 4, "衣衫": 4, "塑料": 4, "一张": 4, "纸片": 4, "如能": 4, "善用": 4, "意味着": 4, "重生": 4, "转给": 4, "最": 4, "身边": 4, "事": 4, "集团军": 4, "录制": 4, "流量": 4, "短": 4, "挺进": 4, "侧翻": 4, "消防官兵": 4, "凉山": 4, "犬": 4, "休息": 4, "故事": 4, "悲伤": 4, "广州": 4, "运送": 4, "四川省委": 4, "工作组": 4, "来到": 4, "牺牲": 4, "张家界": 4, "美景": 4, "知识": 4, "森林": 4, "林场": 4, "可爱": 4, "贵阳": 4, "早点": 4, "著名景点": 4, "贴": 4, "预言": 4, "灵界": 4, "系统": 4, "永竹村": 4, "到来": 4, "冬天": 4, "公益": 4, "官方": 4, "一心": 4, "堂": 4, "汽车": 3, "汗": 3, "黄金": 3, "昨夜": 3, "当晚": 3, "出动": 3, "麻辣": 3, "首游": 3, "记忆里": 3, "童话世界": 3, "季节": 3, "首次": 3, "美如": 3, "童话": 3, "秋后": 3, "依旧": 3, "大半": 3, "多月": 3, "秋季": 3, "大部分": 3, "瀑布": 3, "管理局": 3, "负责人": 3, "介绍": 3, "处于": 3, "排查": 3, "危险源": 3, "维修": 3, "加固": 3, "感觉": 3, "迎来": 3, "剧本": 3, "没人来": 3, "来开": 3, "物业": 3, "收到": 3, "十几次": 3, "邻居": 3, "投诉": 3, "太吵": 3, "不让": 3, "民宿": 3, "断": 3, "收入": 3, "来源": 3, "天才": 3, "轻易": 3, "放过": 3, "出新": 3, "办法": 3, "吃瓜": 3, "自行车": 2, "蛋糕": 2, "没吃过": 2, "改名": 2, "去过": 2, "人生": 2, "一路": 2, "遗憾": 2, "未来": 2, "好好": 2, "梦想": 2, "努力": 2, "夜深": 2, "不想": 2, "睡觉": 2, "记录": 2, "愉快": 2, "心情": 2, "挺": 2, "因祸得福": 2, "化险为夷": 2, "打算": 2, "海边": 2, "大风": 2, "没": 2, "去": 2, "成": 2, "错过": 2, "翘": 2, "高": 2, "党课": 2, "北京": 2, "那场": 2, "特": 2, "大暴雨": 2, "无数": 2, "那本": 2, "情感": 2, "读物": 2, "早安": 2, "房子": 2, "没塌": 2, "爱情": 2, "塌": 2, "送": 2, "某地": 2, "堵车": 2, "滞留": 2, "奔波": 2, "困": 2, "大娘": 2, "端": 2, "热腾腾": 2, "面": 2, "搬": 2, "炎热": 2, "战士": 2, "着装": 2, "公": 2, "转圈": 2, "里": 2, "留下": 2, "美好": 2, "回忆": 2, "联盟": 2, "乌鲁木齐": 2, "云": 2, "谣言": 2, "街": 2, "邯郸": 2, "能救": 2, "威武": 2, "钟": 2, "鼓励": 2, "互助": 2, "男人": 2, "忍耐": 2, "一点": 2, "有限": 2, "妇女": 2, "机票": 2, "旅客": 2, "承担": 2, "晚": 2, "牵动人心": 2, "邢先生": 2, "月初": 2, "朋友": 2, "导致": 2, "团期": 2, "接到": 2, "旅行社": 2, "打": 2, "来": 2, "电话": 2, "团费": 2, "退还": 2, "一部": 2, "壹线": 2, "联合": 2, "伙伴": 2, "一车": 2, "套": 2, "粮油": 2, "个村": 2, "转": 2, "至": 2, "货车": 2, "转运": 2, "前两天": 2, "帐篷": 2, "睡袋": 2, "家庭": 2, "箱": 2, "公司": 2, "第三批": 2, "核心": 2, "沿途": 2, "观测": 2, "出沟": 2, "车上": 2, "跑步": 2, "区域": 2, "电网": 2, "帽子": 2, "相继": 2, "学习": 2, "生存": 2, "灾难": 2, "惊慌失措": 2, "微": 2, "详细": 2, "甘肃省": 2, "公安消防": 2, "命令": 2, "甘南": 2, "集结": 2, "天水": 2, "临夏": 2, "白银": 2, "轻型": 2, "新区": 2, "定西": 2, "绵师": 2, "杂谈": 2, "突发": 2, "混乱": 2, "意识": 2, "武警官兵": 2, "天泪": 2, "传奇": 2, "凤凰": 2, "无双": 2, "多年": 2, "资助": 2, "贫困生": 2, "澎湃": 2, "山东": 2, "邢威敏": 2, "卖": 2, "自称": 2, "第二天": 2, "捐款": 2, "万元": 2, "邢": 2, "学生": 2, "捐款捐物": 2, "小时": 2, "时隔": 2, "三月": 2, "康复": 2, "往日": 2, "藏族": 2, "羌": 2, "互粉": 2, "辟谣": 2, "地震台": 2, "网速": 2, "人数": 2, "增至": 2, "新增": 2, "身份": 2, "重伤": 2, "中断": 2, "线": 2, "抢": 2, "通便": 2, "道": 2, "抢通": 2, "抗震救灾": 2, "忠诚": 2, "点亮": 2, "肥皂": 2, "民警": 2, "交通": 2, "帮": 2, "推车": 2, "偷乐": 2, "他边": 2, "暑假": 2, "秀美": 2, "景色": 2, "令人": 2, "赞叹": 2, "回来": 2, "使人": 2, "惋惜": 2, "不知": 2, "看点": 2, "一组": 2, "执行": 2, "真实": 2, "照片": 2, "第一张": 2, "就让": 2, "忍不住": 2, "哭": 2, "老百姓": 2, "往外": 2, "勇敢": 2, "前线": 2, "这是": 2, "逆行": 2, "直击": 2, "甘肃": 2, "中午": 2, "十二时": 2, "两组": 2, "十人": 2, "突击队": 2, "九道": 2, "拐": 2, "垮塌": 2, "村落": 2, "一部分": 2, "漳扎": 2, "镇上": 2, "寺": 2, "寨": 2, "利用": 2, "蛇眼": 2, "探测": 2, "雷达": 2, "探": 2, "七年": 2, "首播": 2, "首歌": 2, "响应": 2, "赈灾": 2, "特别": 2, "制作": 2, "歌曲": 2, "音乐": 2, "国": 2, "深": 2, "江南": 2, "夜去": 2, "指挥": 2, "乘客": 2, "地带": 2, "地址": 2, "历险记": 2, "四年": 2, "假期": 2, "上课": 2, "训练": 2, "间": 2, "周而复始": 2, "放松": 2, "好不容易": 2, "中考": 2, "七月": 2, "底": 2, "全家": 2, "愿望": 2, "清单": 2, "能量": 2, "文明": 2, "网": 2, "方向": 2, "军粉团": 2, "落叶": 2, "金": 2, "拱门": 2, "王天浩": 2, "墙上": 2, "徒手": 2, "抬车": 2, "保证": 2, "通道": 2, "畅通": 2, "突发状况": 2, "方向向": 2, "外": 2, "小轿车": 2, "横": 2, "衰": 2, "困死": 2, "可怕": 2, "十八名": 2, "平武县": 2, "中学": 2, "休整": 2, "救援队": 2, "犬刚": 2, "普格县": 2, "泥石流": 2, "投入": 2, "生病": 2, "第二次": 2, "座谈会": 2, "听思洁": 2, "同学": 2, "讲": 2, "敲": 2, "爱恨": 2, "纠葛": 2, "馋嘴": 2, "药家鑫": 2, "看法": 2, "家庭教育": 2, "隐患": 2, "深思": 2, "嫉妒": 2, "恐怖": 2, "九年": 2, "纪念": 2, "一场": 2, "美梦": 2, "展开": 2, "全文": 2, "寻人": 2, "车子": 2, "进沟": 2, "失散": 2, "做鬼脸": 2, "沟里": 2, "分批": 2, "走散": 2, "伤势": 2, "大碍": 2, "急需": 2, "妻子": 2, "王锦滔": 2, "陆航": 2, "旅": 2, "四架": 2, "机组": 2, "简单": 2, "西部": 2, "战区": 2, "指挥组": 2, "沟通": 2, "协调": 2, "飞赴": 2, "分钟": 2, "西游记": 2, "取景": 2, "七级": 2, "绵阳": 2, "分队": 2, "黑河": 2, "塘永竹村": 2, "搜寻": 2, "接通": 2, "海事": 2, "卫星电话": 2, "具体位置": 2, "一共": 2, "老人": 2, "小孩": 2, "汇合": 2, "疑问": 2, "车祸": 2, "民兵": 2, "京报": 2, "开启": 2, "之旅": 2, "错失": 2, "国内": 2, "不哭": 2, "有情": 2, "有意": 2, "挺住": 2, "心连心": 2, "人员伤亡": 2, "平平安安": 2, "自救": 2, "幽默": 2, "救治": 2, "重伤员": 2, "国防": 2, "礼物": 2, "三个": 2, "淡季": 2, "高铁": 2, "站": 2, "拥挤": 2, "是因为": 2, "前段时间": 2, "缘故": 2, "贵州": 2, "气温": 2, "家里": 2, "低": 2, "晚上": 2, "风": 2, "穿件": 2, "薄袄": 2, "明天": 2, "起床": 2, "晚安": 2, "员工": 2, "挖出": 2, "遇难": 2, "娱圈": 2, "八妹": 2, "实拍": 2, "海水": 2, "海西": 2, "北约": 2, "早日": 2, "昔日": 2, "驴友": 2, "攻略": 2, "三年": 2, "动": 2, "催化": 2, "金龙": 2, "文字": 2, "脑控": 2, "凡人": 2, "不": 2, "受": 2, "时空": 2, "女娲": 2, "关系": 2, "影视": 2, "穿越": 2, "紧急": 2, "疏散": 2, "路边": 2, "瓦房": 2, "检查": 2, "坍塌": 2, "屋里": 2, "两人": 2, "不肯": 2, "耐心": 2, "劝告": 2, "屋主": 2, "深夜": 2, "不顾": 2, "月底": 2, "受灾地区": 2, "分装": 2, "机构": 2, "工作人员": 2, "寒冷": 2, "保障": 2, "冷": 2, "天猫": 2, "店": 2, "支持": 2, "捐赠": 2, "预备": 2, "一份": 2, "今日": 2, "表情": 2, "致敬": 2, "警察": 2, "警嫂": 2, "祝福": 2, "警宝": 2, "当年": 2, "唐山大": 2, "震惊": 2, "第一次": 2, "感受": 2, "自然": 2, "灾祸": 2, "伤亡": 2, "电影": 2, "王妃": 2, "社区": 2, "鸿翔": 2, "微博": 2, "急救": 2, "已有": 2, "女兵": 2, "保送": 2, "军校": 2, "最右": 1, "矿泉水": 1, "月亮": 1, "凌": 1, "去年": 1, "海子": 1, "西安": 1, "车主": 1, "怼": 1, "西安地区": 1, "震感": 1, "网友": 1, "拍摄": 1, "画面": 1, "显示": 1, "车库": 1, "震到": 1, "撞": 1, "无界乱": 1, "刀客": 1, "左": 1, "哼哼": 1, "一女": 1, "泪流满面": 1, "矿": 1}